<?xml version="1.0" encoding="utf-8"?>
<Feature xmlns="http://schemas.microsoft.com/sharepoint/" Description="SharePoint Add-in Feature" Id="d632d88c-aac0-4828-b5db-ad04b5eaac52" Scope="Web" Title="DOCUMENT_MANAGEMENT Feature1" Version="1.0.0.8">
  <ElementManifests>
    <ElementManifest Location="Pages\Elements.xml" />
    <ElementFile Location="Pages\Default.aspx" />
    <ElementFile Location="Pages\CreateList.aspx" />
    <ElementManifest Location="Scripts\Elements.xml" />
    <ElementFile Location="Scripts\App.js" />
    <ElementFile Location="Scripts\jquery-1.9.1.min.map" />
    <ElementFile Location="Scripts\jquery-1.9.1.min.js" />
    <ElementFile Location="Scripts\jquery-1.9.1.js" />
    <ElementFile Location="Scripts\jquery-1.9.1.intellisense.js" />
    <ElementFile Location="Scripts\AppCommon.js" />
    <ElementFile Location="Scripts\AppPermision.js" />
    <ElementFile Location="Scripts\CreateList.js" />
    <ElementFile Location="Scripts\ListCommonFunction.js" />
    <ElementFile Location="Scripts\ListFunction.js" />
    <ElementManifest Location="Content\Elements.xml" />
    <ElementFile Location="Content\App.css" />
    <ElementFile Location="Content\stylesheet.css" />
    <ElementFile Location="Content\assets\global\css\components.css" />
    <ElementFile Location="Content\assets\global\css\components.min.css" />
    <ElementFile Location="Content\assets\global\css\jquery.treetable.css" />
    <ElementFile Location="Content\assets\global\css\plugins.css" />
    <ElementFile Location="Content\assets\global\css\plugins.min.css" />
    <ElementFile Location="Content\assets\global\dist\cpexcel.js" />
    <ElementFile Location="Content\assets\global\dist\jszip.js" />
    <ElementFile Location="Content\assets\global\dist\shim.min.js" />
    <ElementFile Location="Content\assets\global\dist\xlsx.core.min.js" />
    <ElementFile Location="Content\assets\global\dist\xlsx.core.min.map" />
    <ElementFile Location="Content\assets\global\dist\xlsx.extendscript.js" />
    <ElementFile Location="Content\assets\global\dist\xlsx.full.min.js" />
    <ElementFile Location="Content\assets\global\dist\xlsx.full.min.map" />
    <ElementFile Location="Content\assets\global\dist\xlsx.js" />
    <ElementFile Location="Content\assets\global\dist\xlsx.min.js" />
    <ElementFile Location="Content\assets\global\dist\xlsx.min.map" />
    <ElementFile Location="Content\assets\global\img\EmployeeDefault.jpg" />
    <ElementFile Location="Content\assets\global\img\loading-spinner-grey.gif" />
    <ElementFile Location="Content\assets\global\img\portlet-collapse-icon.png" />
    <ElementFile Location="Content\assets\global\img\remove-icon-small.png" />
    <ElementFile Location="Content\assets\global\plugins\components-date-time-pickers.min.js" />
    <ElementFile Location="Content\assets\global\plugins\ExportExcel.js" />
    <ElementFile Location="Content\assets\global\plugins\jquery.blockui.min.js" />
    <ElementFile Location="Content\assets\global\plugins\jquery.min.js" />
    <ElementFile Location="Content\assets\global\plugins\js.cookie.min.js" />
    <ElementFile Location="Content\assets\global\plugins\moment.min.js" />
    <ElementFile Location="Content\assets\global\plugins\underscore.js" />
    <ElementFile Location="Content\assets\global\plugins\bootstrap\css\bootstrap.css" />
    <ElementFile Location="Content\assets\global\plugins\bootstrap\css\bootstrap.min.css" />
    <ElementFile Location="Content\assets\global\plugins\bootstrap\fonts\bootstrap\glyphicons-halflings-regular.eot" />
    <ElementFile Location="Content\assets\global\plugins\bootstrap\fonts\bootstrap\glyphicons-halflings-regular.svg" />
    <ElementFile Location="Content\assets\global\plugins\bootstrap\fonts\bootstrap\glyphicons-halflings-regular.ttf" />
    <ElementFile Location="Content\assets\global\plugins\bootstrap\fonts\bootstrap\glyphicons-halflings-regular.woff" />
    <ElementFile Location="Content\assets\global\plugins\bootstrap\fonts\bootstrap\glyphicons-halflings-regular.woff2" />
    <ElementFile Location="Content\assets\global\plugins\bootstrap\js\bootstrap.js" />
    <ElementFile Location="Content\assets\global\plugins\bootstrap\js\bootstrap.min.js" />
    <ElementFile Location="Content\assets\global\plugins\bootstrap-datepicker\css\bootstrap-datepicker.css" />
    <ElementFile Location="Content\assets\global\plugins\bootstrap-datepicker\css\bootstrap-datepicker.min.css" />
    <ElementFile Location="Content\assets\global\plugins\bootstrap-datepicker\css\bootstrap-datepicker.standalone.css" />
    <ElementFile Location="Content\assets\global\plugins\bootstrap-datepicker\css\bootstrap-datepicker.standalone.min.css" />
    <ElementFile Location="Content\assets\global\plugins\bootstrap-datepicker\css\bootstrap-datepicker3.css" />
    <ElementFile Location="Content\assets\global\plugins\bootstrap-datepicker\css\bootstrap-datepicker3.min.css" />
    <ElementFile Location="Content\assets\global\plugins\bootstrap-datepicker\css\bootstrap-datepicker3.standalone.css" />
    <ElementFile Location="Content\assets\global\plugins\bootstrap-datepicker\css\bootstrap-datepicker3.standalone.min.css" />
    <ElementFile Location="Content\assets\global\plugins\bootstrap-datepicker\js\bootstrap-datepicker.js" />
    <ElementFile Location="Content\assets\global\plugins\bootstrap-datepicker\js\bootstrap-datepicker.min.js" />
    <ElementFile Location="Content\assets\global\plugins\bootstrap-datepicker\locales\bootstrap-datepicker.ar.min.js" />
    <ElementFile Location="Content\assets\global\plugins\bootstrap-datepicker\locales\bootstrap-datepicker.az.min.js" />
    <ElementFile Location="Content\assets\global\plugins\bootstrap-datepicker\locales\bootstrap-datepicker.bg.min.js" />
    <ElementFile Location="Content\assets\global\plugins\bootstrap-datepicker\locales\bootstrap-datepicker.bs.min.js" />
    <ElementFile Location="Content\assets\global\plugins\bootstrap-datepicker\locales\bootstrap-datepicker.ca.min.js" />
    <ElementFile Location="Content\assets\global\plugins\bootstrap-datepicker\locales\bootstrap-datepicker.cs.min.js" />
    <ElementFile Location="Content\assets\global\plugins\bootstrap-datepicker\locales\bootstrap-datepicker.cy.min.js" />
    <ElementFile Location="Content\assets\global\plugins\bootstrap-datepicker\locales\bootstrap-datepicker.da.min.js" />
    <ElementFile Location="Content\assets\global\plugins\bootstrap-datepicker\locales\bootstrap-datepicker.de.min.js" />
    <ElementFile Location="Content\assets\global\plugins\bootstrap-datepicker\locales\bootstrap-datepicker.el.min.js" />
    <ElementFile Location="Content\assets\global\plugins\bootstrap-datepicker\locales\bootstrap-datepicker.en-GB.min.js" />
    <ElementFile Location="Content\assets\global\plugins\bootstrap-datepicker\locales\bootstrap-datepicker.eo.min.js" />
    <ElementFile Location="Content\assets\global\plugins\bootstrap-datepicker\locales\bootstrap-datepicker.es.min.js" />
    <ElementFile Location="Content\assets\global\plugins\bootstrap-datepicker\locales\bootstrap-datepicker.et.min.js" />
    <ElementFile Location="Content\assets\global\plugins\bootstrap-datepicker\locales\bootstrap-datepicker.eu.min.js" />
    <ElementFile Location="Content\assets\global\plugins\bootstrap-datepicker\locales\bootstrap-datepicker.fa.min.js" />
    <ElementFile Location="Content\assets\global\plugins\bootstrap-datepicker\locales\bootstrap-datepicker.fi.min.js" />
    <ElementFile Location="Content\assets\global\plugins\bootstrap-datepicker\locales\bootstrap-datepicker.fo.min.js" />
    <ElementFile Location="Content\assets\global\plugins\bootstrap-datepicker\locales\bootstrap-datepicker.fr-CH.min.js" />
    <ElementFile Location="Content\assets\global\plugins\bootstrap-datepicker\locales\bootstrap-datepicker.fr.min.js" />
    <ElementFile Location="Content\assets\global\plugins\bootstrap-datepicker\locales\bootstrap-datepicker.gl.min.js" />
    <ElementFile Location="Content\assets\global\plugins\bootstrap-datepicker\locales\bootstrap-datepicker.he.min.js" />
    <ElementFile Location="Content\assets\global\plugins\bootstrap-datepicker\locales\bootstrap-datepicker.hr.min.js" />
    <ElementFile Location="Content\assets\global\plugins\bootstrap-datepicker\locales\bootstrap-datepicker.hu.min.js" />
    <ElementFile Location="Content\assets\global\plugins\bootstrap-datepicker\locales\bootstrap-datepicker.hy.min.js" />
    <ElementFile Location="Content\assets\global\plugins\bootstrap-datepicker\locales\bootstrap-datepicker.id.min.js" />
    <ElementFile Location="Content\assets\global\plugins\bootstrap-datepicker\locales\bootstrap-datepicker.is.min.js" />
    <ElementFile Location="Content\assets\global\plugins\bootstrap-datepicker\locales\bootstrap-datepicker.it-CH.min.js" />
    <ElementFile Location="Content\assets\global\plugins\bootstrap-datepicker\locales\bootstrap-datepicker.it.min.js" />
    <ElementFile Location="Content\assets\global\plugins\bootstrap-datepicker\locales\bootstrap-datepicker.ja.min.js" />
    <ElementFile Location="Content\assets\global\plugins\bootstrap-datepicker\locales\bootstrap-datepicker.ka.min.js" />
    <ElementFile Location="Content\assets\global\plugins\bootstrap-datepicker\locales\bootstrap-datepicker.kh.min.js" />
    <ElementFile Location="Content\assets\global\plugins\bootstrap-datepicker\locales\bootstrap-datepicker.kk.min.js" />
    <ElementFile Location="Content\assets\global\plugins\bootstrap-datepicker\locales\bootstrap-datepicker.ko.min.js" />
    <ElementFile Location="Content\assets\global\plugins\bootstrap-datepicker\locales\bootstrap-datepicker.kr.min.js" />
    <ElementFile Location="Content\assets\global\plugins\bootstrap-datepicker\locales\bootstrap-datepicker.lt.min.js" />
    <ElementFile Location="Content\assets\global\plugins\bootstrap-datepicker\locales\bootstrap-datepicker.lv.min.js" />
    <ElementFile Location="Content\assets\global\plugins\bootstrap-datepicker\locales\bootstrap-datepicker.me.min.js" />
    <ElementFile Location="Content\assets\global\plugins\bootstrap-datepicker\locales\bootstrap-datepicker.mk.min.js" />
    <ElementFile Location="Content\assets\global\plugins\bootstrap-datepicker\locales\bootstrap-datepicker.mn.min.js" />
    <ElementFile Location="Content\assets\global\plugins\bootstrap-datepicker\locales\bootstrap-datepicker.ms.min.js" />
    <ElementFile Location="Content\assets\global\plugins\bootstrap-datepicker\locales\bootstrap-datepicker.nb.min.js" />
    <ElementFile Location="Content\assets\global\plugins\bootstrap-datepicker\locales\bootstrap-datepicker.nl-BE.min.js" />
    <ElementFile Location="Content\assets\global\plugins\bootstrap-datepicker\locales\bootstrap-datepicker.nl.min.js" />
    <ElementFile Location="Content\assets\global\plugins\bootstrap-datepicker\locales\bootstrap-datepicker.no.min.js" />
    <ElementFile Location="Content\assets\global\plugins\bootstrap-datepicker\locales\bootstrap-datepicker.pl.min.js" />
    <ElementFile Location="Content\assets\global\plugins\bootstrap-datepicker\locales\bootstrap-datepicker.pt-BR.min.js" />
    <ElementFile Location="Content\assets\global\plugins\bootstrap-datepicker\locales\bootstrap-datepicker.pt.min.js" />
    <ElementFile Location="Content\assets\global\plugins\bootstrap-datepicker\locales\bootstrap-datepicker.ro.min.js" />
    <ElementFile Location="Content\assets\global\plugins\bootstrap-datepicker\locales\bootstrap-datepicker.rs-latin.min.js" />
    <ElementFile Location="Content\assets\global\plugins\bootstrap-datepicker\locales\bootstrap-datepicker.rs.min.js" />
    <ElementFile Location="Content\assets\global\plugins\bootstrap-datepicker\locales\bootstrap-datepicker.ru.min.js" />
    <ElementFile Location="Content\assets\global\plugins\bootstrap-datepicker\locales\bootstrap-datepicker.sk.min.js" />
    <ElementFile Location="Content\assets\global\plugins\bootstrap-datepicker\locales\bootstrap-datepicker.sl.min.js" />
    <ElementFile Location="Content\assets\global\plugins\bootstrap-datepicker\locales\bootstrap-datepicker.sq.min.js" />
    <ElementFile Location="Content\assets\global\plugins\bootstrap-datepicker\locales\bootstrap-datepicker.sr-latin.min.js" />
    <ElementFile Location="Content\assets\global\plugins\bootstrap-datepicker\locales\bootstrap-datepicker.sr.min.js" />
    <ElementFile Location="Content\assets\global\plugins\bootstrap-datepicker\locales\bootstrap-datepicker.sv.min.js" />
    <ElementFile Location="Content\assets\global\plugins\bootstrap-datepicker\locales\bootstrap-datepicker.sw.min.js" />
    <ElementFile Location="Content\assets\global\plugins\bootstrap-datepicker\locales\bootstrap-datepicker.th.min.js" />
    <ElementFile Location="Content\assets\global\plugins\bootstrap-datepicker\locales\bootstrap-datepicker.tr.min.js" />
    <ElementFile Location="Content\assets\global\plugins\bootstrap-datepicker\locales\bootstrap-datepicker.uk.min.js" />
    <ElementFile Location="Content\assets\global\plugins\bootstrap-datepicker\locales\bootstrap-datepicker.vi.min.js" />
    <ElementFile Location="Content\assets\global\plugins\bootstrap-datepicker\locales\bootstrap-datepicker.zh-CN.min.js" />
    <ElementFile Location="Content\assets\global\plugins\bootstrap-datepicker\locales\bootstrap-datepicker.zh-TW.min.js" />
    <ElementFile Location="Content\assets\global\plugins\bootstrap-daterangepicker\daterangepicker.css" />
    <ElementFile Location="Content\assets\global\plugins\bootstrap-daterangepicker\daterangepicker.js" />
    <ElementFile Location="Content\assets\global\plugins\bootstrap-daterangepicker\daterangepicker.min.css" />
    <ElementFile Location="Content\assets\global\plugins\bootstrap-daterangepicker\daterangepicker.min.js" />
    <ElementFile Location="Content\assets\global\plugins\bootstrap-daterangepicker\README.md" />
    <ElementFile Location="Content\assets\global\plugins\bootstrap-datetimepicker\LICENSE" />
    <ElementFile Location="Content\assets\global\plugins\bootstrap-datetimepicker\README.md" />
    <ElementFile Location="Content\assets\global\plugins\bootstrap-datetimepicker\css\bootstrap-datetimepicker.css" />
    <ElementFile Location="Content\assets\global\plugins\bootstrap-datetimepicker\css\bootstrap-datetimepicker.min.css" />
    <ElementFile Location="Content\assets\global\plugins\bootstrap-datetimepicker\js\bootstrap-datetimepicker.js" />
    <ElementFile Location="Content\assets\global\plugins\bootstrap-datetimepicker\js\bootstrap-datetimepicker.min.js" />
    <ElementFile Location="Content\assets\global\plugins\bootstrap-datetimepicker\js\locales\bootstrap-datetimepicker.ar.js" />
    <ElementFile Location="Content\assets\global\plugins\bootstrap-datetimepicker\js\locales\bootstrap-datetimepicker.az.js" />
    <ElementFile Location="Content\assets\global\plugins\bootstrap-datetimepicker\js\locales\bootstrap-datetimepicker.bg.js" />
    <ElementFile Location="Content\assets\global\plugins\bootstrap-datetimepicker\js\locales\bootstrap-datetimepicker.bn.js" />
    <ElementFile Location="Content\assets\global\plugins\bootstrap-datetimepicker\js\locales\bootstrap-datetimepicker.ca.js" />
    <ElementFile Location="Content\assets\global\plugins\bootstrap-datetimepicker\js\locales\bootstrap-datetimepicker.cs.js" />
    <ElementFile Location="Content\assets\global\plugins\bootstrap-datetimepicker\js\locales\bootstrap-datetimepicker.da.js" />
    <ElementFile Location="Content\assets\global\plugins\bootstrap-datetimepicker\js\locales\bootstrap-datetimepicker.de.js" />
    <ElementFile Location="Content\assets\global\plugins\bootstrap-datetimepicker\js\locales\bootstrap-datetimepicker.ee.js" />
    <ElementFile Location="Content\assets\global\plugins\bootstrap-datetimepicker\js\locales\bootstrap-datetimepicker.el.js" />
    <ElementFile Location="Content\assets\global\plugins\bootstrap-datetimepicker\js\locales\bootstrap-datetimepicker.es.js" />
    <ElementFile Location="Content\assets\global\plugins\bootstrap-datetimepicker\js\locales\bootstrap-datetimepicker.fi.js" />
    <ElementFile Location="Content\assets\global\plugins\bootstrap-datetimepicker\js\locales\bootstrap-datetimepicker.fr.js" />
    <ElementFile Location="Content\assets\global\plugins\bootstrap-datetimepicker\js\locales\bootstrap-datetimepicker.he.js" />
    <ElementFile Location="Content\assets\global\plugins\bootstrap-datetimepicker\js\locales\bootstrap-datetimepicker.hr.js" />
    <ElementFile Location="Content\assets\global\plugins\bootstrap-datetimepicker\js\locales\bootstrap-datetimepicker.hu.js" />
    <ElementFile Location="Content\assets\global\plugins\bootstrap-datetimepicker\js\locales\bootstrap-datetimepicker.hy.js" />
    <ElementFile Location="Content\assets\global\plugins\bootstrap-datetimepicker\js\locales\bootstrap-datetimepicker.id.js" />
    <ElementFile Location="Content\assets\global\plugins\bootstrap-datetimepicker\js\locales\bootstrap-datetimepicker.is.js" />
    <ElementFile Location="Content\assets\global\plugins\bootstrap-datetimepicker\js\locales\bootstrap-datetimepicker.it.js" />
    <ElementFile Location="Content\assets\global\plugins\bootstrap-datetimepicker\js\locales\bootstrap-datetimepicker.ja.js" />
    <ElementFile Location="Content\assets\global\plugins\bootstrap-datetimepicker\js\locales\bootstrap-datetimepicker.ka.js" />
    <ElementFile Location="Content\assets\global\plugins\bootstrap-datetimepicker\js\locales\bootstrap-datetimepicker.ko.js" />
    <ElementFile Location="Content\assets\global\plugins\bootstrap-datetimepicker\js\locales\bootstrap-datetimepicker.lt.js" />
    <ElementFile Location="Content\assets\global\plugins\bootstrap-datetimepicker\js\locales\bootstrap-datetimepicker.lv.js" />
    <ElementFile Location="Content\assets\global\plugins\bootstrap-datetimepicker\js\locales\bootstrap-datetimepicker.ms.js" />
    <ElementFile Location="Content\assets\global\plugins\bootstrap-datetimepicker\js\locales\bootstrap-datetimepicker.nb.js" />
    <ElementFile Location="Content\assets\global\plugins\bootstrap-datetimepicker\js\locales\bootstrap-datetimepicker.nl.js" />
    <ElementFile Location="Content\assets\global\plugins\bootstrap-datetimepicker\js\locales\bootstrap-datetimepicker.no.js" />
    <ElementFile Location="Content\assets\global\plugins\bootstrap-datetimepicker\js\locales\bootstrap-datetimepicker.pl.js" />
    <ElementFile Location="Content\assets\global\plugins\bootstrap-datetimepicker\js\locales\bootstrap-datetimepicker.pt-BR.js" />
    <ElementFile Location="Content\assets\global\plugins\bootstrap-datetimepicker\js\locales\bootstrap-datetimepicker.pt.js" />
    <ElementFile Location="Content\assets\global\plugins\bootstrap-datetimepicker\js\locales\bootstrap-datetimepicker.ro.js" />
    <ElementFile Location="Content\assets\global\plugins\bootstrap-datetimepicker\js\locales\bootstrap-datetimepicker.rs-latin.js" />
    <ElementFile Location="Content\assets\global\plugins\bootstrap-datetimepicker\js\locales\bootstrap-datetimepicker.rs.js" />
    <ElementFile Location="Content\assets\global\plugins\bootstrap-datetimepicker\js\locales\bootstrap-datetimepicker.ru.js" />
    <ElementFile Location="Content\assets\global\plugins\bootstrap-datetimepicker\js\locales\bootstrap-datetimepicker.sk.js" />
    <ElementFile Location="Content\assets\global\plugins\bootstrap-datetimepicker\js\locales\bootstrap-datetimepicker.sl.js" />
    <ElementFile Location="Content\assets\global\plugins\bootstrap-datetimepicker\js\locales\bootstrap-datetimepicker.sv.js" />
    <ElementFile Location="Content\assets\global\plugins\bootstrap-datetimepicker\js\locales\bootstrap-datetimepicker.sw.js" />
    <ElementFile Location="Content\assets\global\plugins\bootstrap-datetimepicker\js\locales\bootstrap-datetimepicker.th.js" />
    <ElementFile Location="Content\assets\global\plugins\bootstrap-datetimepicker\js\locales\bootstrap-datetimepicker.tr.js" />
    <ElementFile Location="Content\assets\global\plugins\bootstrap-datetimepicker\js\locales\bootstrap-datetimepicker.ua.js" />
    <ElementFile Location="Content\assets\global\plugins\bootstrap-datetimepicker\js\locales\bootstrap-datetimepicker.uk.js" />
    <ElementFile Location="Content\assets\global\plugins\bootstrap-datetimepicker\js\locales\bootstrap-datetimepicker.zh-CN.js" />
    <ElementFile Location="Content\assets\global\plugins\bootstrap-datetimepicker\js\locales\bootstrap-datetimepicker.zh-TW.js" />
    <ElementFile Location="Content\assets\global\plugins\bootstrap-fileinput\bootstrap-fileinput.css" />
    <ElementFile Location="Content\assets\global\plugins\bootstrap-fileinput\bootstrap-fileinput.js" />
    <ElementFile Location="Content\assets\global\plugins\bootstrap-markdown\package.json" />
    <ElementFile Location="Content\assets\global\plugins\bootstrap-markdown\README.md" />
    <ElementFile Location="Content\assets\global\plugins\bootstrap-markdown\css\bootstrap-markdown.min.css" />
    <ElementFile Location="Content\assets\global\plugins\bootstrap-markdown\js\bootstrap-markdown.js" />
    <ElementFile Location="Content\assets\global\plugins\bootstrap-markdown\less\bootstrap-markdown.less" />
    <ElementFile Location="Content\assets\global\plugins\bootstrap-markdown\lib\markdown.js" />
    <ElementFile Location="Content\assets\global\plugins\bootstrap-markdown\locale\bootstrap-markdown.ar.js" />
    <ElementFile Location="Content\assets\global\plugins\bootstrap-markdown\locale\bootstrap-markdown.cs.js" />
    <ElementFile Location="Content\assets\global\plugins\bootstrap-markdown\locale\bootstrap-markdown.da.js" />
    <ElementFile Location="Content\assets\global\plugins\bootstrap-markdown\locale\bootstrap-markdown.de.js" />
    <ElementFile Location="Content\assets\global\plugins\bootstrap-markdown\locale\bootstrap-markdown.es.js" />
    <ElementFile Location="Content\assets\global\plugins\bootstrap-markdown\locale\bootstrap-markdown.fr.js" />
    <ElementFile Location="Content\assets\global\plugins\bootstrap-markdown\locale\bootstrap-markdown.ja.js" />
    <ElementFile Location="Content\assets\global\plugins\bootstrap-markdown\locale\bootstrap-markdown.kr.js" />
    <ElementFile Location="Content\assets\global\plugins\bootstrap-markdown\locale\bootstrap-markdown.nb.js" />
    <ElementFile Location="Content\assets\global\plugins\bootstrap-markdown\locale\bootstrap-markdown.nl.js" />
    <ElementFile Location="Content\assets\global\plugins\bootstrap-markdown\locale\bootstrap-markdown.pl.js" />
    <ElementFile Location="Content\assets\global\plugins\bootstrap-markdown\locale\bootstrap-markdown.ru.js" />
    <ElementFile Location="Content\assets\global\plugins\bootstrap-markdown\locale\bootstrap-markdown.sl.js" />
    <ElementFile Location="Content\assets\global\plugins\bootstrap-markdown\locale\bootstrap-markdown.sv.js" />
    <ElementFile Location="Content\assets\global\plugins\bootstrap-markdown\locale\bootstrap-markdown.tr.js" />
    <ElementFile Location="Content\assets\global\plugins\bootstrap-markdown\locale\bootstrap-markdown.ua.js" />
    <ElementFile Location="Content\assets\global\plugins\bootstrap-markdown\locale\bootstrap-markdown.zh.js" />
    <ElementFile Location="Content\assets\global\plugins\bootstrap-summernote\summernote.css" />
    <ElementFile Location="Content\assets\global\plugins\bootstrap-summernote\summernote.js" />
    <ElementFile Location="Content\assets\global\plugins\bootstrap-summernote\summernote.min.js" />
    <ElementFile Location="Content\assets\global\plugins\bootstrap-summernote\font\summernote.eot" />
    <ElementFile Location="Content\assets\global\plugins\bootstrap-summernote\font\summernote.ttf" />
    <ElementFile Location="Content\assets\global\plugins\bootstrap-summernote\font\summernote.woff" />
    <ElementFile Location="Content\assets\global\plugins\bootstrap-summernote\lang\summernote-ar-AR.js" />
    <ElementFile Location="Content\assets\global\plugins\bootstrap-summernote\lang\summernote-ar-AR.min.js" />
    <ElementFile Location="Content\assets\global\plugins\bootstrap-summernote\lang\summernote-bg-BG.js" />
    <ElementFile Location="Content\assets\global\plugins\bootstrap-summernote\lang\summernote-bg-BG.min.js" />
    <ElementFile Location="Content\assets\global\plugins\bootstrap-summernote\lang\summernote-ca-ES.js" />
    <ElementFile Location="Content\assets\global\plugins\bootstrap-summernote\lang\summernote-ca-ES.min.js" />
    <ElementFile Location="Content\assets\global\plugins\bootstrap-summernote\lang\summernote-cs-CZ.js" />
    <ElementFile Location="Content\assets\global\plugins\bootstrap-summernote\lang\summernote-cs-CZ.min.js" />
    <ElementFile Location="Content\assets\global\plugins\bootstrap-summernote\lang\summernote-da-DK.js" />
    <ElementFile Location="Content\assets\global\plugins\bootstrap-summernote\lang\summernote-da-DK.min.js" />
    <ElementFile Location="Content\assets\global\plugins\bootstrap-summernote\lang\summernote-de-DE.js" />
    <ElementFile Location="Content\assets\global\plugins\bootstrap-summernote\lang\summernote-de-DE.min.js" />
    <ElementFile Location="Content\assets\global\plugins\bootstrap-summernote\lang\summernote-es-ES.js" />
    <ElementFile Location="Content\assets\global\plugins\bootstrap-summernote\lang\summernote-es-ES.min.js" />
    <ElementFile Location="Content\assets\global\plugins\bootstrap-summernote\lang\summernote-es-EU.js" />
    <ElementFile Location="Content\assets\global\plugins\bootstrap-summernote\lang\summernote-es-EU.min.js" />
    <ElementFile Location="Content\assets\global\plugins\bootstrap-summernote\lang\summernote-fa-IR.js" />
    <ElementFile Location="Content\assets\global\plugins\bootstrap-summernote\lang\summernote-fa-IR.min.js" />
    <ElementFile Location="Content\assets\global\plugins\bootstrap-summernote\lang\summernote-fi-FI.js" />
    <ElementFile Location="Content\assets\global\plugins\bootstrap-summernote\lang\summernote-fi-FI.min.js" />
    <ElementFile Location="Content\assets\global\plugins\bootstrap-summernote\lang\summernote-fr-FR.js" />
    <ElementFile Location="Content\assets\global\plugins\bootstrap-summernote\lang\summernote-fr-FR.min.js" />
    <ElementFile Location="Content\assets\global\plugins\bootstrap-summernote\lang\summernote-he-IL.js" />
    <ElementFile Location="Content\assets\global\plugins\bootstrap-summernote\lang\summernote-he-IL.min.js" />
    <ElementFile Location="Content\assets\global\plugins\bootstrap-summernote\lang\summernote-hu-HU.js" />
    <ElementFile Location="Content\assets\global\plugins\bootstrap-summernote\lang\summernote-hu-HU.min.js" />
    <ElementFile Location="Content\assets\global\plugins\bootstrap-summernote\lang\summernote-id-ID.js" />
    <ElementFile Location="Content\assets\global\plugins\bootstrap-summernote\lang\summernote-id-ID.min.js" />
    <ElementFile Location="Content\assets\global\plugins\bootstrap-summernote\lang\summernote-it-IT.js" />
    <ElementFile Location="Content\assets\global\plugins\bootstrap-summernote\lang\summernote-it-IT.min.js" />
    <ElementFile Location="Content\assets\global\plugins\bootstrap-summernote\lang\summernote-ja-JP.js" />
    <ElementFile Location="Content\assets\global\plugins\bootstrap-summernote\lang\summernote-ja-JP.min.js" />
    <ElementFile Location="Content\assets\global\plugins\bootstrap-summernote\lang\summernote-ko-KR.js" />
    <ElementFile Location="Content\assets\global\plugins\bootstrap-summernote\lang\summernote-ko-KR.min.js" />
    <ElementFile Location="Content\assets\global\plugins\bootstrap-summernote\lang\summernote-lt-LT.js" />
    <ElementFile Location="Content\assets\global\plugins\bootstrap-summernote\lang\summernote-lt-LT.min.js" />
    <ElementFile Location="Content\assets\global\plugins\bootstrap-summernote\lang\summernote-nb-NO.js" />
    <ElementFile Location="Content\assets\global\plugins\bootstrap-summernote\lang\summernote-nb-NO.min.js" />
    <ElementFile Location="Content\assets\global\plugins\bootstrap-summernote\lang\summernote-nl-NL.js" />
    <ElementFile Location="Content\assets\global\plugins\bootstrap-summernote\lang\summernote-nl-NL.min.js" />
    <ElementFile Location="Content\assets\global\plugins\bootstrap-summernote\lang\summernote-pl-PL.js" />
    <ElementFile Location="Content\assets\global\plugins\bootstrap-summernote\lang\summernote-pl-PL.min.js" />
    <ElementFile Location="Content\assets\global\plugins\bootstrap-summernote\lang\summernote-pt-BR.js" />
    <ElementFile Location="Content\assets\global\plugins\bootstrap-summernote\lang\summernote-pt-BR.min.js" />
    <ElementFile Location="Content\assets\global\plugins\bootstrap-summernote\lang\summernote-pt-PT.js" />
    <ElementFile Location="Content\assets\global\plugins\bootstrap-summernote\lang\summernote-pt-PT.min.js" />
    <ElementFile Location="Content\assets\global\plugins\bootstrap-summernote\lang\summernote-ro-RO.js" />
    <ElementFile Location="Content\assets\global\plugins\bootstrap-summernote\lang\summernote-ro-RO.min.js" />
    <ElementFile Location="Content\assets\global\plugins\bootstrap-summernote\lang\summernote-ru-RU.js" />
    <ElementFile Location="Content\assets\global\plugins\bootstrap-summernote\lang\summernote-ru-RU.min.js" />
    <ElementFile Location="Content\assets\global\plugins\bootstrap-summernote\lang\summernote-sk-SK.js" />
    <ElementFile Location="Content\assets\global\plugins\bootstrap-summernote\lang\summernote-sk-SK.min.js" />
    <ElementFile Location="Content\assets\global\plugins\bootstrap-summernote\lang\summernote-sl-SI.js" />
    <ElementFile Location="Content\assets\global\plugins\bootstrap-summernote\lang\summernote-sl-SI.min.js" />
    <ElementFile Location="Content\assets\global\plugins\bootstrap-summernote\lang\summernote-sr-RS-Latin.js" />
    <ElementFile Location="Content\assets\global\plugins\bootstrap-summernote\lang\summernote-sr-RS-Latin.min.js" />
    <ElementFile Location="Content\assets\global\plugins\bootstrap-summernote\lang\summernote-sr-RS.js" />
    <ElementFile Location="Content\assets\global\plugins\bootstrap-summernote\lang\summernote-sr-RS.min.js" />
    <ElementFile Location="Content\assets\global\plugins\bootstrap-summernote\lang\summernote-sv-SE.js" />
    <ElementFile Location="Content\assets\global\plugins\bootstrap-summernote\lang\summernote-sv-SE.min.js" />
    <ElementFile Location="Content\assets\global\plugins\bootstrap-summernote\lang\summernote-th-TH.js" />
    <ElementFile Location="Content\assets\global\plugins\bootstrap-summernote\lang\summernote-th-TH.min.js" />
    <ElementFile Location="Content\assets\global\plugins\bootstrap-summernote\lang\summernote-tr-TR.js" />
    <ElementFile Location="Content\assets\global\plugins\bootstrap-summernote\lang\summernote-tr-TR.min.js" />
    <ElementFile Location="Content\assets\global\plugins\bootstrap-summernote\lang\summernote-uk-UA.js" />
    <ElementFile Location="Content\assets\global\plugins\bootstrap-summernote\lang\summernote-uk-UA.min.js" />
    <ElementFile Location="Content\assets\global\plugins\bootstrap-summernote\lang\summernote-vi-VN.js" />
    <ElementFile Location="Content\assets\global\plugins\bootstrap-summernote\lang\summernote-vi-VN.min.js" />
    <ElementFile Location="Content\assets\global\plugins\bootstrap-summernote\lang\summernote-zh-CN.js" />
    <ElementFile Location="Content\assets\global\plugins\bootstrap-summernote\lang\summernote-zh-CN.min.js" />
    <ElementFile Location="Content\assets\global\plugins\bootstrap-summernote\lang\summernote-zh-TW.js" />
    <ElementFile Location="Content\assets\global\plugins\bootstrap-summernote\lang\summernote-zh-TW.min.js" />
    <ElementFile Location="Content\assets\global\plugins\bootstrap-switch\LICENSE" />
    <ElementFile Location="Content\assets\global\plugins\bootstrap-switch\README.md" />
    <ElementFile Location="Content\assets\global\plugins\bootstrap-switch\css\bootstrap-switch.css" />
    <ElementFile Location="Content\assets\global\plugins\bootstrap-switch\css\bootstrap-switch.min.css" />
    <ElementFile Location="Content\assets\global\plugins\bootstrap-switch\js\bootstrap-switch.js" />
    <ElementFile Location="Content\assets\global\plugins\bootstrap-switch\js\bootstrap-switch.min.js" />
    <ElementFile Location="Content\assets\global\plugins\bootstrap-timepicker\CHANGELOG.md" />
    <ElementFile Location="Content\assets\global\plugins\bootstrap-timepicker\LICENSE" />
    <ElementFile Location="Content\assets\global\plugins\bootstrap-timepicker\README.md" />
    <ElementFile Location="Content\assets\global\plugins\bootstrap-timepicker\css\bootstrap-timepicker.css" />
    <ElementFile Location="Content\assets\global\plugins\bootstrap-timepicker\css\bootstrap-timepicker.min.css" />
    <ElementFile Location="Content\assets\global\plugins\bootstrap-timepicker\js\bootstrap-timepicker.js" />
    <ElementFile Location="Content\assets\global\plugins\bootstrap-timepicker\js\bootstrap-timepicker.min.js" />
    <ElementFile Location="Content\assets\global\plugins\bootstrap-wysihtml5\bootstrap-wysihtml5.css" />
    <ElementFile Location="Content\assets\global\plugins\bootstrap-wysihtml5\bootstrap-wysihtml5.js" />
    <ElementFile Location="Content\assets\global\plugins\bootstrap-wysihtml5\wysihtml5-0.3.0.js" />
    <ElementFile Location="Content\assets\global\plugins\bootstrap-wysihtml5\wysiwyg-color.css" />
    <ElementFile Location="Content\assets\global\plugins\bootstrap-wysihtml5\locales\bootstrap-wysihtml5.ar-AR.js" />
    <ElementFile Location="Content\assets\global\plugins\bootstrap-wysihtml5\locales\bootstrap-wysihtml5.bg-BG.js" />
    <ElementFile Location="Content\assets\global\plugins\bootstrap-wysihtml5\locales\bootstrap-wysihtml5.ca-CT.js" />
    <ElementFile Location="Content\assets\global\plugins\bootstrap-wysihtml5\locales\bootstrap-wysihtml5.cs-CZ.js" />
    <ElementFile Location="Content\assets\global\plugins\bootstrap-wysihtml5\locales\bootstrap-wysihtml5.da-DK.js" />
    <ElementFile Location="Content\assets\global\plugins\bootstrap-wysihtml5\locales\bootstrap-wysihtml5.de-DE.js" />
    <ElementFile Location="Content\assets\global\plugins\bootstrap-wysihtml5\locales\bootstrap-wysihtml5.el-GR.js" />
    <ElementFile Location="Content\assets\global\plugins\bootstrap-wysihtml5\locales\bootstrap-wysihtml5.es-AR.js" />
    <ElementFile Location="Content\assets\global\plugins\bootstrap-wysihtml5\locales\bootstrap-wysihtml5.es-ES.js" />
    <ElementFile Location="Content\assets\global\plugins\bootstrap-wysihtml5\locales\bootstrap-wysihtml5.fr-FR.js" />
    <ElementFile Location="Content\assets\global\plugins\bootstrap-wysihtml5\locales\bootstrap-wysihtml5.hr-HR.js" />
    <ElementFile Location="Content\assets\global\plugins\bootstrap-wysihtml5\locales\bootstrap-wysihtml5.it-IT.js" />
    <ElementFile Location="Content\assets\global\plugins\bootstrap-wysihtml5\locales\bootstrap-wysihtml5.ja-JP.js" />
    <ElementFile Location="Content\assets\global\plugins\bootstrap-wysihtml5\locales\bootstrap-wysihtml5.ko-KR.js" />
    <ElementFile Location="Content\assets\global\plugins\bootstrap-wysihtml5\locales\bootstrap-wysihtml5.lt-LT.js" />
    <ElementFile Location="Content\assets\global\plugins\bootstrap-wysihtml5\locales\bootstrap-wysihtml5.mo-MD.js" />
    <ElementFile Location="Content\assets\global\plugins\bootstrap-wysihtml5\locales\bootstrap-wysihtml5.nb-NB.js" />
    <ElementFile Location="Content\assets\global\plugins\bootstrap-wysihtml5\locales\bootstrap-wysihtml5.nl-NL.js" />
    <ElementFile Location="Content\assets\global\plugins\bootstrap-wysihtml5\locales\bootstrap-wysihtml5.pl-PL.js" />
    <ElementFile Location="Content\assets\global\plugins\bootstrap-wysihtml5\locales\bootstrap-wysihtml5.pt-BR.js" />
    <ElementFile Location="Content\assets\global\plugins\bootstrap-wysihtml5\locales\bootstrap-wysihtml5.ru-RU.js" />
    <ElementFile Location="Content\assets\global\plugins\bootstrap-wysihtml5\locales\bootstrap-wysihtml5.sk-SK.js" />
    <ElementFile Location="Content\assets\global\plugins\bootstrap-wysihtml5\locales\bootstrap-wysihtml5.sv-SE.js" />
    <ElementFile Location="Content\assets\global\plugins\bootstrap-wysihtml5\locales\bootstrap-wysihtml5.tr-TR.js" />
    <ElementFile Location="Content\assets\global\plugins\bootstrap-wysihtml5\locales\bootstrap-wysihtml5.ua-UA.js" />
    <ElementFile Location="Content\assets\global\plugins\bootstrap-wysihtml5\locales\bootstrap-wysihtml5.zh-CN.js" />
    <ElementFile Location="Content\assets\global\plugins\bootstrap-wysihtml5\locales\bootstrap-wysihtml5.zh-TW.js" />
    <ElementFile Location="Content\assets\global\plugins\clockface\CHANGELOG.txt" />
    <ElementFile Location="Content\assets\global\plugins\clockface\LICENSE-MIT" />
    <ElementFile Location="Content\assets\global\plugins\clockface\README.md" />
    <ElementFile Location="Content\assets\global\plugins\clockface\css\clockface.css" />
    <ElementFile Location="Content\assets\global\plugins\clockface\js\clockface.js" />
    <ElementFile Location="Content\assets\global\plugins\datatables\datatables.all.min.js" />
    <ElementFile Location="Content\assets\global\plugins\datatables\datatables.min.css" />
    <ElementFile Location="Content\assets\global\plugins\datatables\datatables.min.js" />
    <ElementFile Location="Content\assets\global\plugins\datatables\images\back_disabled.png" />
    <ElementFile Location="Content\assets\global\plugins\datatables\images\back_enabled.png" />
    <ElementFile Location="Content\assets\global\plugins\datatables\images\back_enabled_hover.png" />
    <ElementFile Location="Content\assets\global\plugins\datatables\images\forward_disabled.png" />
    <ElementFile Location="Content\assets\global\plugins\datatables\images\forward_enabled.png" />
    <ElementFile Location="Content\assets\global\plugins\datatables\images\forward_enabled_hover.png" />
    <ElementFile Location="Content\assets\global\plugins\datatables\images\sort_asc.png" />
    <ElementFile Location="Content\assets\global\plugins\datatables\images\sort_asc_disabled.png" />
    <ElementFile Location="Content\assets\global\plugins\datatables\images\sort_both.png" />
    <ElementFile Location="Content\assets\global\plugins\datatables\images\sort_desc.png" />
    <ElementFile Location="Content\assets\global\plugins\datatables\images\sort_desc_disabled.png" />
    <ElementFile Location="Content\assets\global\plugins\datatables\images\Sorting icons.psd" />
    <ElementFile Location="Content\assets\global\plugins\datatables\plugins\bootstrap\datatables.bootstrap.css" />
    <ElementFile Location="Content\assets\global\plugins\datatables\plugins\bootstrap\datatables.bootstrap.js" />
    <ElementFile Location="Content\assets\global\plugins\echart\echarts.common.min.js" />
    <ElementFile Location="Content\assets\global\plugins\echart\echarts.min.js" />
    <ElementFile Location="Content\assets\global\plugins\echart\echarts.simple.min.js" />
    <ElementFile Location="Content\assets\global\plugins\font-awesome\css\font-awesome.css" />
    <ElementFile Location="Content\assets\global\plugins\font-awesome\css\font-awesome.min.css" />
    <ElementFile Location="Content\assets\global\plugins\font-awesome\fonts\fontawesome-webfont.eot" />
    <ElementFile Location="Content\assets\global\plugins\font-awesome\fonts\fontawesome-webfont.svg" />
    <ElementFile Location="Content\assets\global\plugins\font-awesome\fonts\fontawesome-webfont.ttf" />
    <ElementFile Location="Content\assets\global\plugins\font-awesome\fonts\fontawesome-webfont.woff" />
    <ElementFile Location="Content\assets\global\plugins\font-awesome\fonts\fontawesome-webfont.woff2" />
    <ElementFile Location="Content\assets\global\plugins\font-awesome\fonts\FontAwesome.otf" />
    <ElementFile Location="Content\assets\global\plugins\fullcalendar\changelog.txt" />
    <ElementFile Location="Content\assets\global\plugins\fullcalendar\fullcalendar.css" />
    <ElementFile Location="Content\assets\global\plugins\fullcalendar\fullcalendar.js" />
    <ElementFile Location="Content\assets\global\plugins\fullcalendar\fullcalendar.min.css" />
    <ElementFile Location="Content\assets\global\plugins\fullcalendar\fullcalendar.min.js" />
    <ElementFile Location="Content\assets\global\plugins\fullcalendar\fullcalendar.print.css" />
    <ElementFile Location="Content\assets\global\plugins\fullcalendar\gcal.js" />
    <ElementFile Location="Content\assets\global\plugins\fullcalendar\lang-all.js" />
    <ElementFile Location="Content\assets\global\plugins\fullcalendar\license.txt" />
    <ElementFile Location="Content\assets\global\plugins\fullcalendar\demos\agenda-views.html" />
    <ElementFile Location="Content\assets\global\plugins\fullcalendar\demos\background-events.html" />
    <ElementFile Location="Content\assets\global\plugins\fullcalendar\demos\basic-views.html" />
    <ElementFile Location="Content\assets\global\plugins\fullcalendar\demos\default.html" />
    <ElementFile Location="Content\assets\global\plugins\fullcalendar\demos\external-dragging.html" />
    <ElementFile Location="Content\assets\global\plugins\fullcalendar\demos\gcal.html" />
    <ElementFile Location="Content\assets\global\plugins\fullcalendar\demos\json.html" />
    <ElementFile Location="Content\assets\global\plugins\fullcalendar\demos\languages.html" />
    <ElementFile Location="Content\assets\global\plugins\fullcalendar\demos\selectable.html" />
    <ElementFile Location="Content\assets\global\plugins\fullcalendar\demos\theme.html" />
    <ElementFile Location="Content\assets\global\plugins\fullcalendar\demos\timezones.html" />
    <ElementFile Location="Content\assets\global\plugins\fullcalendar\demos\json\events.json" />
    <ElementFile Location="Content\assets\global\plugins\fullcalendar\demos\php\get-events.php" />
    <ElementFile Location="Content\assets\global\plugins\fullcalendar\demos\php\get-timezones.php" />
    <ElementFile Location="Content\assets\global\plugins\fullcalendar\demos\php\utils.php" />
    <ElementFile Location="Content\assets\global\plugins\fullcalendar\lang\ar-ma.js" />
    <ElementFile Location="Content\assets\global\plugins\fullcalendar\lang\ar-sa.js" />
    <ElementFile Location="Content\assets\global\plugins\fullcalendar\lang\ar-tn.js" />
    <ElementFile Location="Content\assets\global\plugins\fullcalendar\lang\ar.js" />
    <ElementFile Location="Content\assets\global\plugins\fullcalendar\lang\bg.js" />
    <ElementFile Location="Content\assets\global\plugins\fullcalendar\lang\ca.js" />
    <ElementFile Location="Content\assets\global\plugins\fullcalendar\lang\cs.js" />
    <ElementFile Location="Content\assets\global\plugins\fullcalendar\lang\da.js" />
    <ElementFile Location="Content\assets\global\plugins\fullcalendar\lang\de-at.js" />
    <ElementFile Location="Content\assets\global\plugins\fullcalendar\lang\de.js" />
    <ElementFile Location="Content\assets\global\plugins\fullcalendar\lang\el.js" />
    <ElementFile Location="Content\assets\global\plugins\fullcalendar\lang\en-au.js" />
    <ElementFile Location="Content\assets\global\plugins\fullcalendar\lang\en-ca.js" />
    <ElementFile Location="Content\assets\global\plugins\fullcalendar\lang\en-gb.js" />
    <ElementFile Location="Content\assets\global\plugins\fullcalendar\lang\es.js" />
    <ElementFile Location="Content\assets\global\plugins\fullcalendar\lang\fa.js" />
    <ElementFile Location="Content\assets\global\plugins\fullcalendar\lang\fi.js" />
    <ElementFile Location="Content\assets\global\plugins\fullcalendar\lang\fr-ca.js" />
    <ElementFile Location="Content\assets\global\plugins\fullcalendar\lang\fr.js" />
    <ElementFile Location="Content\assets\global\plugins\fullcalendar\lang\he.js" />
    <ElementFile Location="Content\assets\global\plugins\fullcalendar\lang\hi.js" />
    <ElementFile Location="Content\assets\global\plugins\fullcalendar\lang\hr.js" />
    <ElementFile Location="Content\assets\global\plugins\fullcalendar\lang\hu.js" />
    <ElementFile Location="Content\assets\global\plugins\fullcalendar\lang\id.js" />
    <ElementFile Location="Content\assets\global\plugins\fullcalendar\lang\is.js" />
    <ElementFile Location="Content\assets\global\plugins\fullcalendar\lang\it.js" />
    <ElementFile Location="Content\assets\global\plugins\fullcalendar\lang\ja.js" />
    <ElementFile Location="Content\assets\global\plugins\fullcalendar\lang\ko.js" />
    <ElementFile Location="Content\assets\global\plugins\fullcalendar\lang\lt.js" />
    <ElementFile Location="Content\assets\global\plugins\fullcalendar\lang\lv.js" />
    <ElementFile Location="Content\assets\global\plugins\fullcalendar\lang\nb.js" />
    <ElementFile Location="Content\assets\global\plugins\fullcalendar\lang\nl.js" />
    <ElementFile Location="Content\assets\global\plugins\fullcalendar\lang\pl.js" />
    <ElementFile Location="Content\assets\global\plugins\fullcalendar\lang\pt-br.js" />
    <ElementFile Location="Content\assets\global\plugins\fullcalendar\lang\pt.js" />
    <ElementFile Location="Content\assets\global\plugins\fullcalendar\lang\ro.js" />
    <ElementFile Location="Content\assets\global\plugins\fullcalendar\lang\ru.js" />
    <ElementFile Location="Content\assets\global\plugins\fullcalendar\lang\sk.js" />
    <ElementFile Location="Content\assets\global\plugins\fullcalendar\lang\sl.js" />
    <ElementFile Location="Content\assets\global\plugins\fullcalendar\lang\sr-cyrl.js" />
    <ElementFile Location="Content\assets\global\plugins\fullcalendar\lang\sr.js" />
    <ElementFile Location="Content\assets\global\plugins\fullcalendar\lang\sv.js" />
    <ElementFile Location="Content\assets\global\plugins\fullcalendar\lang\th.js" />
    <ElementFile Location="Content\assets\global\plugins\fullcalendar\lang\tr.js" />
    <ElementFile Location="Content\assets\global\plugins\fullcalendar\lang\uk.js" />
    <ElementFile Location="Content\assets\global\plugins\fullcalendar\lang\vi.js" />
    <ElementFile Location="Content\assets\global\plugins\fullcalendar\lang\zh-cn.js" />
    <ElementFile Location="Content\assets\global\plugins\fullcalendar\lang\zh-tw.js" />
    <ElementFile Location="Content\assets\global\plugins\fullcalendar\lib\jquery-ui.custom.min.js" />
    <ElementFile Location="Content\assets\global\plugins\fullcalendar\lib\jquery.min.js" />
    <ElementFile Location="Content\assets\global\plugins\fullcalendar\lib\moment.min.js" />
    <ElementFile Location="Content\assets\global\plugins\fullcalendar\lib\cupertino\jquery-ui.min.css" />
    <ElementFile Location="Content\assets\global\plugins\fullcalendar\lib\cupertino\images\animated-overlay.gif" />
    <ElementFile Location="Content\assets\global\plugins\fullcalendar\lib\cupertino\images\ui-bg_diagonals-thick_90_eeeeee_40x40.png" />
    <ElementFile Location="Content\assets\global\plugins\fullcalendar\lib\cupertino\images\ui-bg_flat_15_cd0a0a_40x100.png" />
    <ElementFile Location="Content\assets\global\plugins\fullcalendar\lib\cupertino\images\ui-bg_glass_100_e4f1fb_1x400.png" />
    <ElementFile Location="Content\assets\global\plugins\fullcalendar\lib\cupertino\images\ui-bg_glass_50_3baae3_1x400.png" />
    <ElementFile Location="Content\assets\global\plugins\fullcalendar\lib\cupertino\images\ui-bg_glass_80_d7ebf9_1x400.png" />
    <ElementFile Location="Content\assets\global\plugins\fullcalendar\lib\cupertino\images\ui-bg_highlight-hard_100_f2f5f7_1x100.png" />
    <ElementFile Location="Content\assets\global\plugins\fullcalendar\lib\cupertino\images\ui-bg_highlight-hard_70_000000_1x100.png" />
    <ElementFile Location="Content\assets\global\plugins\fullcalendar\lib\cupertino\images\ui-bg_highlight-soft_100_deedf7_1x100.png" />
    <ElementFile Location="Content\assets\global\plugins\fullcalendar\lib\cupertino\images\ui-bg_highlight-soft_25_ffef8f_1x100.png" />
    <ElementFile Location="Content\assets\global\plugins\fullcalendar\lib\cupertino\images\ui-icons_2694e8_256x240.png" />
    <ElementFile Location="Content\assets\global\plugins\fullcalendar\lib\cupertino\images\ui-icons_2e83ff_256x240.png" />
    <ElementFile Location="Content\assets\global\plugins\fullcalendar\lib\cupertino\images\ui-icons_3d80b3_256x240.png" />
    <ElementFile Location="Content\assets\global\plugins\fullcalendar\lib\cupertino\images\ui-icons_72a7cf_256x240.png" />
    <ElementFile Location="Content\assets\global\plugins\fullcalendar\lib\cupertino\images\ui-icons_ffffff_256x240.png" />
    <ElementFile Location="Content\assets\global\plugins\highcharts\js\highcharts-3d.js" />
    <ElementFile Location="Content\assets\global\plugins\highcharts\js\highcharts-3d.src.js" />
    <ElementFile Location="Content\assets\global\plugins\highcharts\js\highcharts-more.js" />
    <ElementFile Location="Content\assets\global\plugins\highcharts\js\highcharts-more.src.js" />
    <ElementFile Location="Content\assets\global\plugins\highcharts\js\highcharts.js" />
    <ElementFile Location="Content\assets\global\plugins\highcharts\js\highcharts.src.js" />
    <ElementFile Location="Content\assets\global\plugins\highcharts\js\adapters\standalone-framework.js" />
    <ElementFile Location="Content\assets\global\plugins\highcharts\js\adapters\standalone-framework.src.js" />
    <ElementFile Location="Content\assets\global\plugins\highcharts\js\modules\boost.js" />
    <ElementFile Location="Content\assets\global\plugins\highcharts\js\modules\boost.src.js" />
    <ElementFile Location="Content\assets\global\plugins\highcharts\js\modules\broken-axis.js" />
    <ElementFile Location="Content\assets\global\plugins\highcharts\js\modules\broken-axis.src.js" />
    <ElementFile Location="Content\assets\global\plugins\highcharts\js\modules\canvas-tools.js" />
    <ElementFile Location="Content\assets\global\plugins\highcharts\js\modules\canvas-tools.src.js" />
    <ElementFile Location="Content\assets\global\plugins\highcharts\js\modules\data.js" />
    <ElementFile Location="Content\assets\global\plugins\highcharts\js\modules\data.src.js" />
    <ElementFile Location="Content\assets\global\plugins\highcharts\js\modules\drilldown.js" />
    <ElementFile Location="Content\assets\global\plugins\highcharts\js\modules\drilldown.src.js" />
    <ElementFile Location="Content\assets\global\plugins\highcharts\js\modules\exporting.js" />
    <ElementFile Location="Content\assets\global\plugins\highcharts\js\modules\exporting.src.js" />
    <ElementFile Location="Content\assets\global\plugins\highcharts\js\modules\funnel.js" />
    <ElementFile Location="Content\assets\global\plugins\highcharts\js\modules\funnel.src.js" />
    <ElementFile Location="Content\assets\global\plugins\highcharts\js\modules\heatmap.js" />
    <ElementFile Location="Content\assets\global\plugins\highcharts\js\modules\heatmap.src.js" />
    <ElementFile Location="Content\assets\global\plugins\highcharts\js\modules\no-data-to-display.js" />
    <ElementFile Location="Content\assets\global\plugins\highcharts\js\modules\no-data-to-display.src.js" />
    <ElementFile Location="Content\assets\global\plugins\highcharts\js\modules\offline-exporting.js" />
    <ElementFile Location="Content\assets\global\plugins\highcharts\js\modules\offline-exporting.src.js" />
    <ElementFile Location="Content\assets\global\plugins\highcharts\js\modules\solid-gauge.js" />
    <ElementFile Location="Content\assets\global\plugins\highcharts\js\modules\solid-gauge.src.js" />
    <ElementFile Location="Content\assets\global\plugins\highcharts\js\modules\treemap.js" />
    <ElementFile Location="Content\assets\global\plugins\highcharts\js\modules\treemap.src.js" />
    <ElementFile Location="Content\assets\global\plugins\highcharts\js\themes\dark-blue.js" />
    <ElementFile Location="Content\assets\global\plugins\highcharts\js\themes\dark-green.js" />
    <ElementFile Location="Content\assets\global\plugins\highcharts\js\themes\dark-unica.js" />
    <ElementFile Location="Content\assets\global\plugins\highcharts\js\themes\gray.js" />
    <ElementFile Location="Content\assets\global\plugins\highcharts\js\themes\grid-light.js" />
    <ElementFile Location="Content\assets\global\plugins\highcharts\js\themes\grid.js" />
    <ElementFile Location="Content\assets\global\plugins\highcharts\js\themes\sand-signika.js" />
    <ElementFile Location="Content\assets\global\plugins\highcharts\js\themes\skies.js" />
    <ElementFile Location="Content\assets\global\plugins\icheck\.gitignore" />
    <ElementFile Location="Content\assets\global\plugins\icheck\bower.json" />
    <ElementFile Location="Content\assets\global\plugins\icheck\CHANGELOG.md" />
    <ElementFile Location="Content\assets\global\plugins\icheck\icheck.jquery.json" />
    <ElementFile Location="Content\assets\global\plugins\icheck\icheck.js" />
    <ElementFile Location="Content\assets\global\plugins\icheck\icheck.min.js" />
    <ElementFile Location="Content\assets\global\plugins\icheck\README.md" />
    <ElementFile Location="Content\assets\global\plugins\icheck\demo\index.html" />
    <ElementFile Location="Content\assets\global\plugins\icheck\demo\css\banner.jpg" />
    <ElementFile Location="Content\assets\global\plugins\icheck\demo\css\custom.css" />
    <ElementFile Location="Content\assets\global\plugins\icheck\demo\css\icheck.png" />
    <ElementFile Location="Content\assets\global\plugins\icheck\demo\css\montserrat-bold.eot" />
    <ElementFile Location="Content\assets\global\plugins\icheck\demo\css\montserrat-bold.svg" />
    <ElementFile Location="Content\assets\global\plugins\icheck\demo\css\montserrat-bold.ttf" />
    <ElementFile Location="Content\assets\global\plugins\icheck\demo\css\montserrat-bold.woff" />
    <ElementFile Location="Content\assets\global\plugins\icheck\demo\css\montserrat-regular.eot" />
    <ElementFile Location="Content\assets\global\plugins\icheck\demo\css\montserrat-regular.svg" />
    <ElementFile Location="Content\assets\global\plugins\icheck\demo\css\montserrat-regular.ttf" />
    <ElementFile Location="Content\assets\global\plugins\icheck\demo\css\montserrat-regular.woff" />
    <ElementFile Location="Content\assets\global\plugins\icheck\demo\css\normalize.css" />
    <ElementFile Location="Content\assets\global\plugins\icheck\demo\css\ie\arrow-bottom.png" />
    <ElementFile Location="Content\assets\global\plugins\icheck\demo\css\ie\arrow-top.png" />
    <ElementFile Location="Content\assets\global\plugins\icheck\demo\css\ie\header-line.png" />
    <ElementFile Location="Content\assets\global\plugins\icheck\demo\css\ie\icon-fork.png" />
    <ElementFile Location="Content\assets\global\plugins\icheck\demo\css\ie\icon-github.png" />
    <ElementFile Location="Content\assets\global\plugins\icheck\demo\css\ie\icon-lab.png" />
    <ElementFile Location="Content\assets\global\plugins\icheck\demo\css\ie\icon-options.png" />
    <ElementFile Location="Content\assets\global\plugins\icheck\demo\css\ie\icon-star.png" />
    <ElementFile Location="Content\assets\global\plugins\icheck\demo\js\custom.min.js" />
    <ElementFile Location="Content\assets\global\plugins\icheck\demo\js\jquery.js" />
    <ElementFile Location="Content\assets\global\plugins\icheck\demo\js\zepto.js" />
    <ElementFile Location="Content\assets\global\plugins\icheck\skins\all.css" />
    <ElementFile Location="Content\assets\global\plugins\icheck\skins\flat\_all.css" />
    <ElementFile Location="Content\assets\global\plugins\icheck\skins\flat\aero.css" />
    <ElementFile Location="Content\assets\global\plugins\icheck\skins\flat\aero.png" />
    <ElementFile Location="Content\assets\global\plugins\icheck\skins\flat\aero_2x.png" />
    <ElementFile Location="Content\assets\global\plugins\icheck\skins\flat\blue.css" />
    <ElementFile Location="Content\assets\global\plugins\icheck\skins\flat\blue.png" />
    <ElementFile Location="Content\assets\global\plugins\icheck\skins\flat\blue_2x.png" />
    <ElementFile Location="Content\assets\global\plugins\icheck\skins\flat\flat.css" />
    <ElementFile Location="Content\assets\global\plugins\icheck\skins\flat\flat.png" />
    <ElementFile Location="Content\assets\global\plugins\icheck\skins\flat\flat_2x.png" />
    <ElementFile Location="Content\assets\global\plugins\icheck\skins\flat\green.css" />
    <ElementFile Location="Content\assets\global\plugins\icheck\skins\flat\green.png" />
    <ElementFile Location="Content\assets\global\plugins\icheck\skins\flat\green_2x.png" />
    <ElementFile Location="Content\assets\global\plugins\icheck\skins\flat\grey.css" />
    <ElementFile Location="Content\assets\global\plugins\icheck\skins\flat\grey.png" />
    <ElementFile Location="Content\assets\global\plugins\icheck\skins\flat\grey_2x.png" />
    <ElementFile Location="Content\assets\global\plugins\icheck\skins\flat\orange.css" />
    <ElementFile Location="Content\assets\global\plugins\icheck\skins\flat\orange.png" />
    <ElementFile Location="Content\assets\global\plugins\icheck\skins\flat\orange_2x.png" />
    <ElementFile Location="Content\assets\global\plugins\icheck\skins\flat\pink.css" />
    <ElementFile Location="Content\assets\global\plugins\icheck\skins\flat\pink.png" />
    <ElementFile Location="Content\assets\global\plugins\icheck\skins\flat\pink_2x.png" />
    <ElementFile Location="Content\assets\global\plugins\icheck\skins\flat\purple.css" />
    <ElementFile Location="Content\assets\global\plugins\icheck\skins\flat\purple.png" />
    <ElementFile Location="Content\assets\global\plugins\icheck\skins\flat\purple_2x.png" />
    <ElementFile Location="Content\assets\global\plugins\icheck\skins\flat\red.css" />
    <ElementFile Location="Content\assets\global\plugins\icheck\skins\flat\red.png" />
    <ElementFile Location="Content\assets\global\plugins\icheck\skins\flat\red_2x.png" />
    <ElementFile Location="Content\assets\global\plugins\icheck\skins\flat\yellow.css" />
    <ElementFile Location="Content\assets\global\plugins\icheck\skins\flat\yellow.png" />
    <ElementFile Location="Content\assets\global\plugins\icheck\skins\flat\yellow_2x.png" />
    <ElementFile Location="Content\assets\global\plugins\icheck\skins\futurico\futurico.css" />
    <ElementFile Location="Content\assets\global\plugins\icheck\skins\futurico\futurico.png" />
    <ElementFile Location="Content\assets\global\plugins\icheck\skins\futurico\futurico_2x.png" />
    <ElementFile Location="Content\assets\global\plugins\icheck\skins\line\_all.css" />
    <ElementFile Location="Content\assets\global\plugins\icheck\skins\line\aero.css" />
    <ElementFile Location="Content\assets\global\plugins\icheck\skins\line\blue.css" />
    <ElementFile Location="Content\assets\global\plugins\icheck\skins\line\green.css" />
    <ElementFile Location="Content\assets\global\plugins\icheck\skins\line\grey.css" />
    <ElementFile Location="Content\assets\global\plugins\icheck\skins\line\line.css" />
    <ElementFile Location="Content\assets\global\plugins\icheck\skins\line\line.png" />
    <ElementFile Location="Content\assets\global\plugins\icheck\skins\line\line_2x.png" />
    <ElementFile Location="Content\assets\global\plugins\icheck\skins\line\orange.css" />
    <ElementFile Location="Content\assets\global\plugins\icheck\skins\line\pink.css" />
    <ElementFile Location="Content\assets\global\plugins\icheck\skins\line\purple.css" />
    <ElementFile Location="Content\assets\global\plugins\icheck\skins\line\red.css" />
    <ElementFile Location="Content\assets\global\plugins\icheck\skins\line\yellow.css" />
    <ElementFile Location="Content\assets\global\plugins\icheck\skins\minimal\_all.css" />
    <ElementFile Location="Content\assets\global\plugins\icheck\skins\minimal\aero.css" />
    <ElementFile Location="Content\assets\global\plugins\icheck\skins\minimal\aero.png" />
    <ElementFile Location="Content\assets\global\plugins\icheck\skins\minimal\aero_2x.png" />
    <ElementFile Location="Content\assets\global\plugins\icheck\skins\minimal\blue.css" />
    <ElementFile Location="Content\assets\global\plugins\icheck\skins\minimal\blue.png" />
    <ElementFile Location="Content\assets\global\plugins\icheck\skins\minimal\blue_2x.png" />
    <ElementFile Location="Content\assets\global\plugins\icheck\skins\minimal\green.css" />
    <ElementFile Location="Content\assets\global\plugins\icheck\skins\minimal\green.png" />
    <ElementFile Location="Content\assets\global\plugins\icheck\skins\minimal\green_2x.png" />
    <ElementFile Location="Content\assets\global\plugins\icheck\skins\minimal\grey.css" />
    <ElementFile Location="Content\assets\global\plugins\icheck\skins\minimal\grey.png" />
    <ElementFile Location="Content\assets\global\plugins\icheck\skins\minimal\grey_2x.png" />
    <ElementFile Location="Content\assets\global\plugins\icheck\skins\minimal\minimal.css" />
    <ElementFile Location="Content\assets\global\plugins\icheck\skins\minimal\minimal.png" />
    <ElementFile Location="Content\assets\global\plugins\icheck\skins\minimal\minimal_2x.png" />
    <ElementFile Location="Content\assets\global\plugins\icheck\skins\minimal\orange.css" />
    <ElementFile Location="Content\assets\global\plugins\icheck\skins\minimal\orange.png" />
    <ElementFile Location="Content\assets\global\plugins\icheck\skins\minimal\orange_2x.png" />
    <ElementFile Location="Content\assets\global\plugins\icheck\skins\minimal\pink.css" />
    <ElementFile Location="Content\assets\global\plugins\icheck\skins\minimal\pink.png" />
    <ElementFile Location="Content\assets\global\plugins\icheck\skins\minimal\pink_2x.png" />
    <ElementFile Location="Content\assets\global\plugins\icheck\skins\minimal\purple.css" />
    <ElementFile Location="Content\assets\global\plugins\icheck\skins\minimal\purple.png" />
    <ElementFile Location="Content\assets\global\plugins\icheck\skins\minimal\purple_2x.png" />
    <ElementFile Location="Content\assets\global\plugins\icheck\skins\minimal\red.css" />
    <ElementFile Location="Content\assets\global\plugins\icheck\skins\minimal\red.png" />
    <ElementFile Location="Content\assets\global\plugins\icheck\skins\minimal\red_2x.png" />
    <ElementFile Location="Content\assets\global\plugins\icheck\skins\minimal\yellow.css" />
    <ElementFile Location="Content\assets\global\plugins\icheck\skins\minimal\yellow.png" />
    <ElementFile Location="Content\assets\global\plugins\icheck\skins\minimal\yellow_2x.png" />
    <ElementFile Location="Content\assets\global\plugins\icheck\skins\polaris\polaris.css" />
    <ElementFile Location="Content\assets\global\plugins\icheck\skins\polaris\polaris.png" />
    <ElementFile Location="Content\assets\global\plugins\icheck\skins\polaris\polaris_2x.png" />
    <ElementFile Location="Content\assets\global\plugins\icheck\skins\square\_all.css" />
    <ElementFile Location="Content\assets\global\plugins\icheck\skins\square\aero.css" />
    <ElementFile Location="Content\assets\global\plugins\icheck\skins\square\aero.png" />
    <ElementFile Location="Content\assets\global\plugins\icheck\skins\square\aero_2x.png" />
    <ElementFile Location="Content\assets\global\plugins\icheck\skins\square\blue.css" />
    <ElementFile Location="Content\assets\global\plugins\icheck\skins\square\blue.png" />
    <ElementFile Location="Content\assets\global\plugins\icheck\skins\square\blue_2x.png" />
    <ElementFile Location="Content\assets\global\plugins\icheck\skins\square\green.css" />
    <ElementFile Location="Content\assets\global\plugins\icheck\skins\square\green.png" />
    <ElementFile Location="Content\assets\global\plugins\icheck\skins\square\green_2x.png" />
    <ElementFile Location="Content\assets\global\plugins\icheck\skins\square\grey.css" />
    <ElementFile Location="Content\assets\global\plugins\icheck\skins\square\grey.png" />
    <ElementFile Location="Content\assets\global\plugins\icheck\skins\square\grey_2x.png" />
    <ElementFile Location="Content\assets\global\plugins\icheck\skins\square\orange.css" />
    <ElementFile Location="Content\assets\global\plugins\icheck\skins\square\orange.png" />
    <ElementFile Location="Content\assets\global\plugins\icheck\skins\square\orange_2x.png" />
    <ElementFile Location="Content\assets\global\plugins\icheck\skins\square\pink.css" />
    <ElementFile Location="Content\assets\global\plugins\icheck\skins\square\pink.png" />
    <ElementFile Location="Content\assets\global\plugins\icheck\skins\square\pink_2x.png" />
    <ElementFile Location="Content\assets\global\plugins\icheck\skins\square\purple.css" />
    <ElementFile Location="Content\assets\global\plugins\icheck\skins\square\purple.png" />
    <ElementFile Location="Content\assets\global\plugins\icheck\skins\square\purple_2x.png" />
    <ElementFile Location="Content\assets\global\plugins\icheck\skins\square\red.css" />
    <ElementFile Location="Content\assets\global\plugins\icheck\skins\square\red.png" />
    <ElementFile Location="Content\assets\global\plugins\icheck\skins\square\red_2x.png" />
    <ElementFile Location="Content\assets\global\plugins\icheck\skins\square\square.css" />
    <ElementFile Location="Content\assets\global\plugins\icheck\skins\square\square.png" />
    <ElementFile Location="Content\assets\global\plugins\icheck\skins\square\square_2x.png" />
    <ElementFile Location="Content\assets\global\plugins\icheck\skins\square\yellow.css" />
    <ElementFile Location="Content\assets\global\plugins\icheck\skins\square\yellow.png" />
    <ElementFile Location="Content\assets\global\plugins\icheck\skins\square\yellow_2x.png" />
    <ElementFile Location="Content\assets\global\plugins\import-excel\excelplus-2.5.js" />
    <ElementFile Location="Content\assets\global\plugins\import-excel\excelplus-2.5.min.js" />
    <ElementFile Location="Content\assets\global\plugins\jquery-repeater\jquery.repeater.js" />
    <ElementFile Location="Content\assets\global\plugins\jquery-repeater\jquery.repeater.min.js" />
    <ElementFile Location="Content\assets\global\plugins\jquery-slimscroll\jquery.slimscroll.js" />
    <ElementFile Location="Content\assets\global\plugins\jquery-slimscroll\jquery.slimscroll.min.js" />
    <ElementFile Location="Content\assets\global\plugins\jquery-slimscroll\README.md" />
    <ElementFile Location="Content\assets\global\plugins\jquery-slimscroll\slimScroll.jquery.json" />
    <ElementFile Location="Content\assets\global\plugins\jquery-ui\jquery-ui.min.css" />
    <ElementFile Location="Content\assets\global\plugins\jquery-ui\jquery-ui.min.js" />
    <ElementFile Location="Content\assets\global\plugins\jquery-ui\LICENSE.txt" />
    <ElementFile Location="Content\assets\global\plugins\jquery-ui\images\ui-icons_444444_256x240.png" />
    <ElementFile Location="Content\assets\global\plugins\jquery-ui\images\ui-icons_555555_256x240.png" />
    <ElementFile Location="Content\assets\global\plugins\jquery-ui\images\ui-icons_777620_256x240.png" />
    <ElementFile Location="Content\assets\global\plugins\jquery-ui\images\ui-icons_777777_256x240.png" />
    <ElementFile Location="Content\assets\global\plugins\jquery-ui\images\ui-icons_cc0000_256x240.png" />
    <ElementFile Location="Content\assets\global\plugins\jquery-ui\images\ui-icons_ffffff_256x240.png" />
    <ElementFile Location="Content\assets\global\plugins\jquery-validation\README.md" />
    <ElementFile Location="Content\assets\global\plugins\jquery-validation\js\additional-methods.js" />
    <ElementFile Location="Content\assets\global\plugins\jquery-validation\js\additional-methods.min.js" />
    <ElementFile Location="Content\assets\global\plugins\jquery-validation\js\jquery.validate.js" />
    <ElementFile Location="Content\assets\global\plugins\jquery-validation\js\jquery.validate.min.js" />
    <ElementFile Location="Content\assets\global\plugins\jquery-validation\js\localization\messages_ar.js" />
    <ElementFile Location="Content\assets\global\plugins\jquery-validation\js\localization\messages_ar.min.js" />
    <ElementFile Location="Content\assets\global\plugins\jquery-validation\js\localization\messages_bg.js" />
    <ElementFile Location="Content\assets\global\plugins\jquery-validation\js\localization\messages_bg.min.js" />
    <ElementFile Location="Content\assets\global\plugins\jquery-validation\js\localization\messages_bn_BD.js" />
    <ElementFile Location="Content\assets\global\plugins\jquery-validation\js\localization\messages_bn_BD.min.js" />
    <ElementFile Location="Content\assets\global\plugins\jquery-validation\js\localization\messages_ca.js" />
    <ElementFile Location="Content\assets\global\plugins\jquery-validation\js\localization\messages_ca.min.js" />
    <ElementFile Location="Content\assets\global\plugins\jquery-validation\js\localization\messages_cs.js" />
    <ElementFile Location="Content\assets\global\plugins\jquery-validation\js\localization\messages_cs.min.js" />
    <ElementFile Location="Content\assets\global\plugins\jquery-validation\js\localization\messages_da.js" />
    <ElementFile Location="Content\assets\global\plugins\jquery-validation\js\localization\messages_da.min.js" />
    <ElementFile Location="Content\assets\global\plugins\jquery-validation\js\localization\messages_de.js" />
    <ElementFile Location="Content\assets\global\plugins\jquery-validation\js\localization\messages_de.min.js" />
    <ElementFile Location="Content\assets\global\plugins\jquery-validation\js\localization\messages_el.js" />
    <ElementFile Location="Content\assets\global\plugins\jquery-validation\js\localization\messages_el.min.js" />
    <ElementFile Location="Content\assets\global\plugins\jquery-validation\js\localization\messages_es.js" />
    <ElementFile Location="Content\assets\global\plugins\jquery-validation\js\localization\messages_es.min.js" />
    <ElementFile Location="Content\assets\global\plugins\jquery-validation\js\localization\messages_es_AR.js" />
    <ElementFile Location="Content\assets\global\plugins\jquery-validation\js\localization\messages_es_AR.min.js" />
    <ElementFile Location="Content\assets\global\plugins\jquery-validation\js\localization\messages_es_PE.js" />
    <ElementFile Location="Content\assets\global\plugins\jquery-validation\js\localization\messages_es_PE.min.js" />
    <ElementFile Location="Content\assets\global\plugins\jquery-validation\js\localization\messages_et.js" />
    <ElementFile Location="Content\assets\global\plugins\jquery-validation\js\localization\messages_et.min.js" />
    <ElementFile Location="Content\assets\global\plugins\jquery-validation\js\localization\messages_eu.js" />
    <ElementFile Location="Content\assets\global\plugins\jquery-validation\js\localization\messages_eu.min.js" />
    <ElementFile Location="Content\assets\global\plugins\jquery-validation\js\localization\messages_fa.js" />
    <ElementFile Location="Content\assets\global\plugins\jquery-validation\js\localization\messages_fa.min.js" />
    <ElementFile Location="Content\assets\global\plugins\jquery-validation\js\localization\messages_fi.js" />
    <ElementFile Location="Content\assets\global\plugins\jquery-validation\js\localization\messages_fi.min.js" />
    <ElementFile Location="Content\assets\global\plugins\jquery-validation\js\localization\messages_fr.js" />
    <ElementFile Location="Content\assets\global\plugins\jquery-validation\js\localization\messages_fr.min.js" />
    <ElementFile Location="Content\assets\global\plugins\jquery-validation\js\localization\messages_ge.js" />
    <ElementFile Location="Content\assets\global\plugins\jquery-validation\js\localization\messages_ge.min.js" />
    <ElementFile Location="Content\assets\global\plugins\jquery-validation\js\localization\messages_gl.js" />
    <ElementFile Location="Content\assets\global\plugins\jquery-validation\js\localization\messages_gl.min.js" />
    <ElementFile Location="Content\assets\global\plugins\jquery-validation\js\localization\messages_he.js" />
    <ElementFile Location="Content\assets\global\plugins\jquery-validation\js\localization\messages_he.min.js" />
    <ElementFile Location="Content\assets\global\plugins\jquery-validation\js\localization\messages_hr.js" />
    <ElementFile Location="Content\assets\global\plugins\jquery-validation\js\localization\messages_hr.min.js" />
    <ElementFile Location="Content\assets\global\plugins\jquery-validation\js\localization\messages_hu.js" />
    <ElementFile Location="Content\assets\global\plugins\jquery-validation\js\localization\messages_hu.min.js" />
    <ElementFile Location="Content\assets\global\plugins\jquery-validation\js\localization\messages_hy_AM.js" />
    <ElementFile Location="Content\assets\global\plugins\jquery-validation\js\localization\messages_hy_AM.min.js" />
    <ElementFile Location="Content\assets\global\plugins\jquery-validation\js\localization\messages_id.js" />
    <ElementFile Location="Content\assets\global\plugins\jquery-validation\js\localization\messages_id.min.js" />
    <ElementFile Location="Content\assets\global\plugins\jquery-validation\js\localization\messages_is.js" />
    <ElementFile Location="Content\assets\global\plugins\jquery-validation\js\localization\messages_is.min.js" />
    <ElementFile Location="Content\assets\global\plugins\jquery-validation\js\localization\messages_it.js" />
    <ElementFile Location="Content\assets\global\plugins\jquery-validation\js\localization\messages_it.min.js" />
    <ElementFile Location="Content\assets\global\plugins\jquery-validation\js\localization\messages_ja.js" />
    <ElementFile Location="Content\assets\global\plugins\jquery-validation\js\localization\messages_ja.min.js" />
    <ElementFile Location="Content\assets\global\plugins\jquery-validation\js\localization\messages_ka.js" />
    <ElementFile Location="Content\assets\global\plugins\jquery-validation\js\localization\messages_ka.min.js" />
    <ElementFile Location="Content\assets\global\plugins\jquery-validation\js\localization\messages_kk.js" />
    <ElementFile Location="Content\assets\global\plugins\jquery-validation\js\localization\messages_kk.min.js" />
    <ElementFile Location="Content\assets\global\plugins\jquery-validation\js\localization\messages_ko.js" />
    <ElementFile Location="Content\assets\global\plugins\jquery-validation\js\localization\messages_ko.min.js" />
    <ElementFile Location="Content\assets\global\plugins\jquery-validation\js\localization\messages_lt.js" />
    <ElementFile Location="Content\assets\global\plugins\jquery-validation\js\localization\messages_lt.min.js" />
    <ElementFile Location="Content\assets\global\plugins\jquery-validation\js\localization\messages_lv.js" />
    <ElementFile Location="Content\assets\global\plugins\jquery-validation\js\localization\messages_lv.min.js" />
    <ElementFile Location="Content\assets\global\plugins\jquery-validation\js\localization\messages_my.js" />
    <ElementFile Location="Content\assets\global\plugins\jquery-validation\js\localization\messages_my.min.js" />
    <ElementFile Location="Content\assets\global\plugins\jquery-validation\js\localization\messages_nl.js" />
    <ElementFile Location="Content\assets\global\plugins\jquery-validation\js\localization\messages_nl.min.js" />
    <ElementFile Location="Content\assets\global\plugins\jquery-validation\js\localization\messages_no.js" />
    <ElementFile Location="Content\assets\global\plugins\jquery-validation\js\localization\messages_no.min.js" />
    <ElementFile Location="Content\assets\global\plugins\jquery-validation\js\localization\messages_pl.js" />
    <ElementFile Location="Content\assets\global\plugins\jquery-validation\js\localization\messages_pl.min.js" />
    <ElementFile Location="Content\assets\global\plugins\jquery-validation\js\localization\messages_pt_BR.js" />
    <ElementFile Location="Content\assets\global\plugins\jquery-validation\js\localization\messages_pt_BR.min.js" />
    <ElementFile Location="Content\assets\global\plugins\jquery-validation\js\localization\messages_pt_PT.js" />
    <ElementFile Location="Content\assets\global\plugins\jquery-validation\js\localization\messages_pt_PT.min.js" />
    <ElementFile Location="Content\assets\global\plugins\jquery-validation\js\localization\messages_ro.js" />
    <ElementFile Location="Content\assets\global\plugins\jquery-validation\js\localization\messages_ro.min.js" />
    <ElementFile Location="Content\assets\global\plugins\jquery-validation\js\localization\messages_ru.js" />
    <ElementFile Location="Content\assets\global\plugins\jquery-validation\js\localization\messages_ru.min.js" />
    <ElementFile Location="Content\assets\global\plugins\jquery-validation\js\localization\messages_si.js" />
    <ElementFile Location="Content\assets\global\plugins\jquery-validation\js\localization\messages_si.min.js" />
    <ElementFile Location="Content\assets\global\plugins\jquery-validation\js\localization\messages_sk.js" />
    <ElementFile Location="Content\assets\global\plugins\jquery-validation\js\localization\messages_sk.min.js" />
    <ElementFile Location="Content\assets\global\plugins\jquery-validation\js\localization\messages_sl.js" />
    <ElementFile Location="Content\assets\global\plugins\jquery-validation\js\localization\messages_sl.min.js" />
    <ElementFile Location="Content\assets\global\plugins\jquery-validation\js\localization\messages_sr.js" />
    <ElementFile Location="Content\assets\global\plugins\jquery-validation\js\localization\messages_sr.min.js" />
    <ElementFile Location="Content\assets\global\plugins\jquery-validation\js\localization\messages_sr_lat.js" />
    <ElementFile Location="Content\assets\global\plugins\jquery-validation\js\localization\messages_sr_lat.min.js" />
    <ElementFile Location="Content\assets\global\plugins\jquery-validation\js\localization\messages_sv.js" />
    <ElementFile Location="Content\assets\global\plugins\jquery-validation\js\localization\messages_sv.min.js" />
    <ElementFile Location="Content\assets\global\plugins\jquery-validation\js\localization\messages_th.js" />
    <ElementFile Location="Content\assets\global\plugins\jquery-validation\js\localization\messages_th.min.js" />
    <ElementFile Location="Content\assets\global\plugins\jquery-validation\js\localization\messages_tj.js" />
    <ElementFile Location="Content\assets\global\plugins\jquery-validation\js\localization\messages_tj.min.js" />
    <ElementFile Location="Content\assets\global\plugins\jquery-validation\js\localization\messages_tr.js" />
    <ElementFile Location="Content\assets\global\plugins\jquery-validation\js\localization\messages_tr.min.js" />
    <ElementFile Location="Content\assets\global\plugins\jquery-validation\js\localization\messages_uk.js" />
    <ElementFile Location="Content\assets\global\plugins\jquery-validation\js\localization\messages_uk.min.js" />
    <ElementFile Location="Content\assets\global\plugins\jquery-validation\js\localization\messages_vi.js" />
    <ElementFile Location="Content\assets\global\plugins\jquery-validation\js\localization\messages_vi.min.js" />
    <ElementFile Location="Content\assets\global\plugins\jquery-validation\js\localization\messages_zh.js" />
    <ElementFile Location="Content\assets\global\plugins\jquery-validation\js\localization\messages_zh.min.js" />
    <ElementFile Location="Content\assets\global\plugins\jquery-validation\js\localization\messages_zh_TW.js" />
    <ElementFile Location="Content\assets\global\plugins\jquery-validation\js\localization\messages_zh_TW.min.js" />
    <ElementFile Location="Content\assets\global\plugins\jquery-validation\js\localization\methods_de.js" />
    <ElementFile Location="Content\assets\global\plugins\jquery-validation\js\localization\methods_de.min.js" />
    <ElementFile Location="Content\assets\global\plugins\jquery-validation\js\localization\methods_es_CL.js" />
    <ElementFile Location="Content\assets\global\plugins\jquery-validation\js\localization\methods_es_CL.min.js" />
    <ElementFile Location="Content\assets\global\plugins\jquery-validation\js\localization\methods_fi.js" />
    <ElementFile Location="Content\assets\global\plugins\jquery-validation\js\localization\methods_fi.min.js" />
    <ElementFile Location="Content\assets\global\plugins\jquery-validation\js\localization\methods_nl.js" />
    <ElementFile Location="Content\assets\global\plugins\jquery-validation\js\localization\methods_nl.min.js" />
    <ElementFile Location="Content\assets\global\plugins\jquery-validation\js\localization\methods_pt.js" />
    <ElementFile Location="Content\assets\global\plugins\jquery-validation\js\localization\methods_pt.min.js" />
    <ElementFile Location="Content\assets\global\plugins\jqvmap\.gitignore" />
    <ElementFile Location="Content\assets\global\plugins\jqvmap\README.md" />
    <ElementFile Location="Content\assets\global\plugins\jqvmap\jqvmap\jquery.vmap.js" />
    <ElementFile Location="Content\assets\global\plugins\jqvmap\jqvmap\jquery.vmap.min.js" />
    <ElementFile Location="Content\assets\global\plugins\jqvmap\jqvmap\jquery.vmap.packed.js" />
    <ElementFile Location="Content\assets\global\plugins\jqvmap\jqvmap\jqvmap.css" />
    <ElementFile Location="Content\assets\global\plugins\jqvmap\jqvmap\data\jquery.vmap.sampledata.js" />
    <ElementFile Location="Content\assets\global\plugins\jqvmap\jqvmap\maps\jquery.vmap.europe.js" />
    <ElementFile Location="Content\assets\global\plugins\jqvmap\jqvmap\maps\jquery.vmap.germany.js" />
    <ElementFile Location="Content\assets\global\plugins\jqvmap\jqvmap\maps\jquery.vmap.russia.js" />
    <ElementFile Location="Content\assets\global\plugins\jqvmap\jqvmap\maps\jquery.vmap.usa.js" />
    <ElementFile Location="Content\assets\global\plugins\jqvmap\jqvmap\maps\jquery.vmap.world.js" />
    <ElementFile Location="Content\assets\global\plugins\jqvmap\samples\europe.html" />
    <ElementFile Location="Content\assets\global\plugins\jqvmap\samples\germany.html" />
    <ElementFile Location="Content\assets\global\plugins\jqvmap\samples\multi.html" />
    <ElementFile Location="Content\assets\global\plugins\jqvmap\samples\russia.html" />
    <ElementFile Location="Content\assets\global\plugins\jqvmap\samples\usa.html" />
    <ElementFile Location="Content\assets\global\plugins\jqvmap\samples\world.html" />
    <ElementFile Location="Content\assets\global\plugins\mdbboostrap\css\mdb.min.css" />
    <ElementFile Location="Content\assets\global\plugins\mdbboostrap\css\toastr.min.css" />
    <ElementFile Location="Content\assets\global\plugins\mdbboostrap\js\mdb.min.js" />
    <ElementFile Location="Content\assets\global\plugins\mdbboostrap\js\toastr.min.js" />
    <ElementFile Location="Content\assets\global\plugins\Organization\CSS\jHTree.css" />
    <ElementFile Location="Content\assets\global\plugins\Organization\js\jquery-1.10.2.js" />
    <ElementFile Location="Content\assets\global\plugins\Organization\js\jquery-ui-1.10.4.custom.min.js" />
    <ElementFile Location="Content\assets\global\plugins\Organization\js\jQuery.jHTree.js" />
    <ElementFile Location="Content\assets\global\plugins\Organization\Themes\smoothness\jquery-ui-1.10.4.custom.css" />
    <ElementFile Location="Content\assets\global\plugins\Organization\Themes\smoothness\jquery-ui-1.10.4.custom.min.css" />
    <ElementFile Location="Content\assets\global\plugins\Organization\Themes\smoothness\images\animated-overlay.gif" />
    <ElementFile Location="Content\assets\global\plugins\Organization\Themes\smoothness\images\ui-bg_flat_0_aaaaaa_40x100.png" />
    <ElementFile Location="Content\assets\global\plugins\Organization\Themes\smoothness\images\ui-bg_flat_75_ffffff_40x100.png" />
    <ElementFile Location="Content\assets\global\plugins\Organization\Themes\smoothness\images\ui-bg_glass_55_fbf9ee_1x400.png" />
    <ElementFile Location="Content\assets\global\plugins\Organization\Themes\smoothness\images\ui-bg_glass_65_ffffff_1x400.png" />
    <ElementFile Location="Content\assets\global\plugins\Organization\Themes\smoothness\images\ui-bg_glass_75_dadada_1x400.png" />
    <ElementFile Location="Content\assets\global\plugins\Organization\Themes\smoothness\images\ui-bg_glass_75_e6e6e6_1x400.png" />
    <ElementFile Location="Content\assets\global\plugins\Organization\Themes\smoothness\images\ui-bg_glass_95_fef1ec_1x400.png" />
    <ElementFile Location="Content\assets\global\plugins\Organization\Themes\smoothness\images\ui-bg_highlight-soft_75_cccccc_1x100.png" />
    <ElementFile Location="Content\assets\global\plugins\Organization\Themes\smoothness\images\ui-icons_222222_256x240.png" />
    <ElementFile Location="Content\assets\global\plugins\Organization\Themes\smoothness\images\ui-icons_2e83ff_256x240.png" />
    <ElementFile Location="Content\assets\global\plugins\Organization\Themes\smoothness\images\ui-icons_454545_256x240.png" />
    <ElementFile Location="Content\assets\global\plugins\Organization\Themes\smoothness\images\ui-icons_888888_256x240.png" />
    <ElementFile Location="Content\assets\global\plugins\Organization\Themes\smoothness\images\ui-icons_cd0a0a_256x240.png" />
    <ElementFile Location="Content\assets\global\plugins\select2\LICENSE.md" />
    <ElementFile Location="Content\assets\global\plugins\select2\README.md" />
    <ElementFile Location="Content\assets\global\plugins\select2\css\select2-bootstrap.min.css" />
    <ElementFile Location="Content\assets\global\plugins\select2\css\select2.css" />
    <ElementFile Location="Content\assets\global\plugins\select2\css\select2.min.css" />
    <ElementFile Location="Content\assets\global\plugins\select2\js\select2.full.js" />
    <ElementFile Location="Content\assets\global\plugins\select2\js\select2.full.min.js" />
    <ElementFile Location="Content\assets\global\plugins\select2\js\select2.js" />
    <ElementFile Location="Content\assets\global\plugins\select2\js\select2.min.js" />
    <ElementFile Location="Content\assets\global\plugins\select2\js\i18n\ar.js" />
    <ElementFile Location="Content\assets\global\plugins\select2\js\i18n\az.js" />
    <ElementFile Location="Content\assets\global\plugins\select2\js\i18n\bg.js" />
    <ElementFile Location="Content\assets\global\plugins\select2\js\i18n\ca.js" />
    <ElementFile Location="Content\assets\global\plugins\select2\js\i18n\cs.js" />
    <ElementFile Location="Content\assets\global\plugins\select2\js\i18n\da.js" />
    <ElementFile Location="Content\assets\global\plugins\select2\js\i18n\de.js" />
    <ElementFile Location="Content\assets\global\plugins\select2\js\i18n\el.js" />
    <ElementFile Location="Content\assets\global\plugins\select2\js\i18n\en.js" />
    <ElementFile Location="Content\assets\global\plugins\select2\js\i18n\es.js" />
    <ElementFile Location="Content\assets\global\plugins\select2\js\i18n\et.js" />
    <ElementFile Location="Content\assets\global\plugins\select2\js\i18n\eu.js" />
    <ElementFile Location="Content\assets\global\plugins\select2\js\i18n\fa.js" />
    <ElementFile Location="Content\assets\global\plugins\select2\js\i18n\fi.js" />
    <ElementFile Location="Content\assets\global\plugins\select2\js\i18n\fr.js" />
    <ElementFile Location="Content\assets\global\plugins\select2\js\i18n\gl.js" />
    <ElementFile Location="Content\assets\global\plugins\select2\js\i18n\he.js" />
    <ElementFile Location="Content\assets\global\plugins\select2\js\i18n\hi.js" />
    <ElementFile Location="Content\assets\global\plugins\select2\js\i18n\hr.js" />
    <ElementFile Location="Content\assets\global\plugins\select2\js\i18n\hu.js" />
    <ElementFile Location="Content\assets\global\plugins\select2\js\i18n\id.js" />
    <ElementFile Location="Content\assets\global\plugins\select2\js\i18n\is.js" />
    <ElementFile Location="Content\assets\global\plugins\select2\js\i18n\it.js" />
    <ElementFile Location="Content\assets\global\plugins\select2\js\i18n\ja.js" />
    <ElementFile Location="Content\assets\global\plugins\select2\js\i18n\km.js" />
    <ElementFile Location="Content\assets\global\plugins\select2\js\i18n\ko.js" />
    <ElementFile Location="Content\assets\global\plugins\select2\js\i18n\lt.js" />
    <ElementFile Location="Content\assets\global\plugins\select2\js\i18n\lv.js" />
    <ElementFile Location="Content\assets\global\plugins\select2\js\i18n\mk.js" />
    <ElementFile Location="Content\assets\global\plugins\select2\js\i18n\ms.js" />
    <ElementFile Location="Content\assets\global\plugins\select2\js\i18n\nb.js" />
    <ElementFile Location="Content\assets\global\plugins\select2\js\i18n\nl.js" />
    <ElementFile Location="Content\assets\global\plugins\select2\js\i18n\pl.js" />
    <ElementFile Location="Content\assets\global\plugins\select2\js\i18n\pt-BR.js" />
    <ElementFile Location="Content\assets\global\plugins\select2\js\i18n\pt.js" />
    <ElementFile Location="Content\assets\global\plugins\select2\js\i18n\ro.js" />
    <ElementFile Location="Content\assets\global\plugins\select2\js\i18n\ru.js" />
    <ElementFile Location="Content\assets\global\plugins\select2\js\i18n\sk.js" />
    <ElementFile Location="Content\assets\global\plugins\select2\js\i18n\sr-Cyrl.js" />
    <ElementFile Location="Content\assets\global\plugins\select2\js\i18n\sr.js" />
    <ElementFile Location="Content\assets\global\plugins\select2\js\i18n\sv.js" />
    <ElementFile Location="Content\assets\global\plugins\select2\js\i18n\th.js" />
    <ElementFile Location="Content\assets\global\plugins\select2\js\i18n\tr.js" />
    <ElementFile Location="Content\assets\global\plugins\select2\js\i18n\uk.js" />
    <ElementFile Location="Content\assets\global\plugins\select2\js\i18n\vi.js" />
    <ElementFile Location="Content\assets\global\plugins\select2\js\i18n\zh-CN.js" />
    <ElementFile Location="Content\assets\global\plugins\select2\js\i18n\zh-TW.js" />
    <ElementFile Location="Content\assets\global\plugins\select2\sass\select2-bootstrap.min.scss" />
    <ElementFile Location="Content\assets\global\plugins\simple-line-icons\icons-lte-ie7.js" />
    <ElementFile Location="Content\assets\global\plugins\simple-line-icons\License.txt" />
    <ElementFile Location="Content\assets\global\plugins\simple-line-icons\Readme.txt" />
    <ElementFile Location="Content\assets\global\plugins\simple-line-icons\simple-line-icons.css" />
    <ElementFile Location="Content\assets\global\plugins\simple-line-icons\simple-line-icons.min.css" />
    <ElementFile Location="Content\assets\global\plugins\simple-line-icons\fonts\Simple-Line-Icons.dev.svg" />
    <ElementFile Location="Content\assets\global\plugins\simple-line-icons\fonts\Simple-Line-Icons.eot" />
    <ElementFile Location="Content\assets\global\plugins\simple-line-icons\fonts\Simple-Line-Icons.svg" />
    <ElementFile Location="Content\assets\global\plugins\simple-line-icons\fonts\Simple-Line-Icons.ttf" />
    <ElementFile Location="Content\assets\global\plugins\simple-line-icons\fonts\Simple-Line-Icons.woff" />
    <ElementFile Location="Content\assets\global\plugins\tree\32px.png" />
    <ElementFile Location="Content\assets\global\plugins\tree\empty_folder.svg" />
    <ElementFile Location="Content\assets\global\plugins\tree\File-icon-24.png" />
    <ElementFile Location="Content\assets\global\plugins\tree\Folder-icon-24.png" />
    <ElementFile Location="Content\assets\global\plugins\tree\folder.svg" />
    <ElementFile Location="Content\assets\global\plugins\tree\jstree.min.js" />
    <ElementFile Location="Content\assets\global\plugins\tree\style.min.css" />
    <ElementFile Location="Content\assets\global\plugins\tree\throbber.gif" />
    <ElementFile Location="Content\assets\global\scripts\app.js" />
    <ElementFile Location="Content\assets\global\scripts\app.min.js" />
    <ElementFile Location="Content\assets\global\scripts\datatable.js" />
    <ElementFile Location="Content\assets\global\scripts\datatable.min.js" />
    <ElementFile Location="Content\assets\global\scripts\jquery.treetable.js" />
    <ElementFile Location="Content\assets\layouts\global\scripts\quick-nav.js" />
    <ElementFile Location="Content\assets\layouts\global\scripts\quick-nav.min.js" />
    <ElementFile Location="Content\assets\layouts\global\scripts\quick-sidebar.js" />
    <ElementFile Location="Content\assets\layouts\global\scripts\quick-sidebar.min.js" />
    <ElementFile Location="Content\assets\layouts\layout\css\custom.css" />
    <ElementFile Location="Content\assets\layouts\layout\css\custom.min.css" />
    <ElementFile Location="Content\assets\layouts\layout\css\layout.css" />
    <ElementFile Location="Content\assets\layouts\layout\css\layout.min.css" />
    <ElementFile Location="Content\assets\layouts\layout\css\themes\blue.css" />
    <ElementFile Location="Content\assets\layouts\layout\css\themes\blue.min.css" />
    <ElementFile Location="Content\assets\layouts\layout\css\themes\darkblue.css" />
    <ElementFile Location="Content\assets\layouts\layout\css\themes\darkblue.min.css" />
    <ElementFile Location="Content\assets\layouts\layout\css\themes\default.css" />
    <ElementFile Location="Content\assets\layouts\layout\css\themes\default.min.css" />
    <ElementFile Location="Content\assets\layouts\layout\css\themes\fecon.css" />
    <ElementFile Location="Content\assets\layouts\layout\css\themes\fecon.min.css" />
    <ElementFile Location="Content\assets\layouts\layout\css\themes\grey.css" />
    <ElementFile Location="Content\assets\layouts\layout\css\themes\grey.min.css" />
    <ElementFile Location="Content\assets\layouts\layout\css\themes\light.css" />
    <ElementFile Location="Content\assets\layouts\layout\css\themes\light.min.css" />
    <ElementFile Location="Content\assets\layouts\layout\css\themes\light2.css" />
    <ElementFile Location="Content\assets\layouts\layout\css\themes\light2.min.css" />
    <ElementFile Location="Content\assets\layouts\layout\img\icon-color-close.png" />
    <ElementFile Location="Content\assets\layouts\layout\img\icon-color.png" />
    <ElementFile Location="Content\assets\layouts\layout\img\logo.png" />
    <ElementFile Location="Content\assets\layouts\layout\img\logo_excel.jpg" />
    <ElementFile Location="Content\assets\layouts\layout\img\logo_excel.PNG" />
    <ElementFile Location="Content\assets\layouts\layout\img\photo3.jpg" />
    <ElementFile Location="Content\assets\layouts\layout\scripts\demo.js" />
    <ElementFile Location="Content\assets\layouts\layout\scripts\demo.min.js" />
    <ElementFile Location="Content\assets\layouts\layout\scripts\layout.js" />
    <ElementFile Location="Content\assets\layouts\layout\scripts\layout.min.js" />
    <ElementFile Location="Content\assets\pages\scripts\components-date-time-pickers.min.js" />
    <ElementFile Location="Content\assets\pages\scripts\components-editors.min.js" />
    <ElementFile Location="Content\assets\TreeGrid\javascript.js" />
    <ElementFile Location="Content\assets\TreeGrid\jquery.treegrid.bootstrap3.min.js" />
    <ElementFile Location="Content\assets\TreeGrid\jquery.treegrid.css" />
    <ElementFile Location="Content\assets\TreeGrid\jquery.treegrid.js" />
    <ElementFile Location="Content\assets\TreeGrid\jquery.treegrid.min.css" />
    <ElementFile Location="Content\assets\TreeGrid\jquery.treegrid.min.js" />
    <ElementFile Location="Content\assets\TreeGrid\TreeGridCustomize.js" />
    <ElementFile Location="Content\assets\global\plugins\excelplus-2.5.min.js" />
    <ElementFile Location="Content\assets\global\plugins\xlsx.core.min.js" />
    <ElementManifest Location="Images\Elements.xml" />
    <ElementFile Location="Images\AppIcon.png" />
    <ElementManifest Location="AppConfig\Elements.xml" />
    <ElementFile Location="AppConfig\Schema.xml" />
    <ElementManifest Location="AppConfigInstance\Elements.xml" />
  </ElementManifests>
  <UpgradeActions>
    <VersionRange>
      <ApplyElementManifests>
        <ElementManifest Location="Pages\Elements.xml" />
        <ElementManifest Location="Scripts\Elements.xml" />
        <ElementManifest Location="Content\Elements.xml" />
        <ElementManifest Location="Images\Elements.xml" />
        <ElementManifest Location="AppConfig\Elements.xml" />
        <ElementManifest Location="AppConfigInstance\Elements.xml" />
      </ApplyElementManifests>
    </VersionRange>
  </UpgradeActions>
</Feature>